{
  "version": "207f310177ab4334a91d86b3dae52fc8",
  "result": {
    "pages": 1,
    "data": [
      {
        "SECUCODE": "001389.SZ",
        "SECURITY_CODE": "001389",
        "SECURITY_NAME_ABBR": "广合科技",
        "ORG_NAME": "广州广合科技股份有限公司",
        "FORMERNAME": null,
        "STR_CODEH": "01989.HK",
        "STR_NAMEH": "广合科技",
        "REGIONBK": "广东省",
        "EM2016": "电子设备-电子元件-电子元件",
        "BLGAINIAN": "5G概念,人工智能,华为概念,PCB,存储芯片,通信技术,AH股,深成500,融资融券,中证500,深股通,昨日涨停,MSCI中国,昨日涨停_含一字,百元股,昨日首板,昨日高振幅,中盘股,中盘成长,近期新高,历史新高 ,百日新高 ,2025年报预增,2026一季报预增,科技风格,题材股",
        "CHAIRMAN": "肖红星",
        "LEGAL_PERSON": "肖红星",
        "PRESIDENT": "曾红",
        "SECRETARY": "曾杨清",
        "FOUND_DATE": "2002-06-17 00:00:00",
        "REG_CAPITAL": 47256.4764,
        "TOTAL_NUM": 4998,
        "TATOLNUMBER": 13,
        "ORG_TEL": "020-82211188-2885",
        "ORG_EMAIL": "stock@delton.com.cn",
        "ORG_WEB": "www.delton.com.cn",
        "ADDRESS": "广州保税区保盈南路22号,香港铜锣湾希慎道33号利园一期19楼1928室",
        "REG_ADDRESS": "广州保税区保盈南路22号",
        "ORG_PROFIE": "    广州广合科技股份有限公司(以下简称“公司”)于2002年在广州市黄埔区成立,2024年在深圳证券交易所主板挂牌上市,股票代码为:001389,股票简称为:广合科技。公司总部位于广州市黄埔开发区,生产基地主要分布在广东广州和湖北黄石。我们拥有高端的研发技术团队、优秀的管理团队以及国内外顶尖的自动化生产线。公司多年来一直致力于打造成为集高端优质PCB产品的研发、生产、销售、服务为一体的行业领先电路板制造企业。广合科技一直致力于以高速、高频为主的高端PCB制造,产品主要应用于数据中心、云计算、工业互联网、人工智能、5G通讯、汽车电子、安防和打印等终端领域。广合科技长期服务于国内外知名客户。多年来,公司规模和技术能力在PCB领域保持持续快速成长,并连续多年被公司主要客户评定为优秀供应商和长期战略合作伙伴。我们注重公司品牌价值、产品研发、产品品质、营销策略、企业文化的打造,通过先进的前沿技术,制造出优质的产品,打造便捷的产品渠道,提供贴心、快捷的售后服务,独创具有特色的运营管理模式,以“服务客户”为宗旨,为推进“智能制造”同步发展的新业态结构建设提供创新动力和重要支持,我们立誓成为国内外PCB产业发展的领航者。在用人方面,公司始终坚持以德为本、德才兼备、不拘一格、能者居上的用人原则,致力于发掘和培养人才,并为其提供可持续发展的机会和丰厚的薪酬福利,达成公司、客户、职工三赢。在此我们诚邀各路精英加盟,并衷心希望您的才能在这里得到充分的发挥,让我们携起手来共创辉煌!",
        "MAIN_BUSINESS": "多高层印制电路板的研发、生产与销售",
        "STR_CODEB": null,
        "STR_NAMEB": null,
        "STR_CODEA": "001389.SZ",
        "STR_NAMEA": "广合科技",
        "SECURITY_CODE_TYPE": 5,
        "SECURITY_TYPE_CODE": "058001001",
        "IS_INNOVATION": 0,
        "SECURITY_PINYIN": "GHKJ",
        "LISTING_DATE": "2024-04-02 00:00:00",
        "TRADE_MARKET": "深交所主板",
        "TRADE_MARKET_CODE": "069001002001",
        "SECURITY_INNER_CODE": "1002488772",
        "ORG_CODE": "10490813",
        "LISTING_STATE": "0",
        "SECURITY_TYPE": "A股",
        "ORG_TYPE": "通用",
        "CODE_TYPE": "ABStock",
        "ORG_TYPE_CODE": "4",
        "CURRENCY": "CNY",
        "ACCOUNT_FIRM": "安永会计师事务所,容诚会计师事务所(特殊普通合伙)",
        "LEGAL_ADVISER": "上海市锦天城(深圳)律师事务所,普衡律师事务所(香港)有限法律责任合伙,Starry Law Firm (Thailand) Co., Ltd.",
        "EXPAND_NAME_ABBR": null,
        "EXPAND_NAME_ABBRN": null,
        "ORG_PROFILE": "广合科技，半导体行业领先，高端PCB产品制造。",
        "SECUCODE_N": "001389.SZ",
        "CORRECODE": "001389",
        "CORRECODE_INNER_CODE": "1002488772",
        "SWINDUSTRY_CODE2": null,
        "SWINDUSTRY_NAME2": null,
        "CSRC_INDUSTRY_NAME": "制造业-计算机、通信和其他电子设备制造业",
        "BOARD_CODE_BK_1LEVEL": "BK1201",
        "BOARD_NAME_1LEVEL": "电子",
        "BOARD_CODE_BK_2LEVEL": "BK0459",
        "BOARD_NAME_2LEVEL": "元件",
        "BOARD_CODE_BK_3LEVEL": "BK1340",
        "BOARD_NAME_3LEVEL": "印制电路板",
        "BLGAINIAN_CODE": "BK0714,BK0800,BK0854,BK0877,BK1137,BK1650,BK0499,BK0568,BK0596,BK0701,BK0804,BK0815,BK0821,BK1050,BK1059,BK1630,BK1633,BK1664,BK1669,BK1674,BK1675,BK1676,BK1677,BK1680,BK1713,BK1717",
        "ORG_FORM": "大型民企",
        "ISSUE_PRICE": 17.43,
        "IS_JUMP_CHAIRMAN": "0",
        "IS_JUMP_LEGALPERSON": "0",
        "IS_JUMP_PRESIDENT": "0",
        "IS_JUMP_SECRETARY": "0",
        "CONTROL_HOLDER": "广州臻蕴投资有限公司",
        "CONTROL_HOLDER_CODE": "10000148112",
        "IS_JUMP_CONTROL": "1",
        "CONTROL_DIRECT_RATIO": "36.22%",
        "CONTROL_INDIRECT_RATIO": "36.22%",
        "REAL_CONTROLER": "肖红星、刘锦婵",
        "REAL_CONTROLER_CODE": "肖红星、刘锦婵",
        "IS_JUMP_REAL": "0、0",
        "REAL_DIRECT_RATIO": "--、--",
        "REAL_INDIRECT_RATIO": "0.61%、0.04%",
        "MAX_DATE": "2026-03-31 00:00:00",
        "MAXPROFIT_PRODUCT": "PCB板",
        "GROSS_PROFIT_RATIO": 80.72,
        "INCOME_STRU_NAME": "PCB板、其他业务",
        "INCOME_STRU_RATIO": "93.01%、6.99%",
        "ADD_BUSINESS": null,
        "ADD_BUSINESS_RATIO": null,
        "PRODUCT_NAME": "印制电路板",
        "AREA_BOARD_NAME": "广东板块",
        "AREA_BOARD_CODE": "BK0153",
        "PRODUCT_CODE": "PRD000001269",
        "IS_USE": "1",
        "INCOME_STRU_NAMENEW": "PCB板；其他业务",
        "INCOME_STRU_RATIONEW": "93.01%；6.99%",
        "ORG_NAME_EN": "Delton Technology (Guangzhou) Inc.",
        "TRADE_MARKET_ZF": "深圳证券交易所",
        "SECPRESENT": "陈炜亮,黄淑芳",
        "INDEDIRECTORS": "张瑾,施凌,陈丽梅",
        "PROVINCE": "广东",
        "ADDRESS_POSTCODE": "510730",
        "REG_NUM": "91440116739749431N",
        "BUSINESS_SCOPE": "电力电子技术服务;智能机器系统技术服务;无人机系统技术服务;信息系统安全服务;电子元件及组件制造;印制电路板制造;货物进出口(专营专控商品除外)",
        "EXPAND_NAME_PINYIN": null,
        "HOST_BROKER": null,
        "TRANSFER_WAY": null,
        "MARKETING_START_DATE": null,
        "MARKET_MAKER": null,
        "TRADE_MARKET_TYPE": null,
        "ORG_FAX": "020-82210929"
      }
    ],
    "count": 1
  },
  "success": true,
  "message": "ok",
  "code": 0
}