{
  "version": "927e6f8ee49070e44e0cd24e68e5c42e",
  "result": {
    "pages": 1,
    "data": [
      {
        "SECUCODE": "002947.SZ",
        "SECURITY_CODE": "002947",
        "SECURITY_NAME_ABBR": "恒铭达",
        "ORG_NAME": "苏州恒铭达电子科技股份有限公司",
        "FORMERNAME": null,
        "STR_CODEH": null,
        "STR_NAMEH": null,
        "REGIONBK": "江苏省",
        "EM2016": "电子设备-电子设备制造-电子设备制造",
        "BLGAINIAN": "苹果概念,5G概念,虚拟现实,华为概念,无线耳机,数据中心,消费电子概念,通信技术,社保重仓,股权激励,融资融券,深股通,专精特新,昨日高振幅,小盘股,小盘成长",
        "CHAIRMAN": "荆世平",
        "LEGAL_PERSON": "荆天平",
        "PRESIDENT": "荆天平",
        "SECRETARY": "王宁丹",
        "FOUND_DATE": "2011-07-27 00:00:00",
        "REG_CAPITAL": 25620.9336,
        "TOTAL_NUM": 2365,
        "TATOLNUMBER": 14,
        "ORG_TEL": "0512-5765566,0512-57655668",
        "ORG_EMAIL": "hmd_zq@hengmingdaks.com",
        "ORG_WEB": "www.hengmingda.com",
        "ADDRESS": "昆山市巴城镇石牌塔基路1568号",
        "REG_ADDRESS": "昆山市巴城镇石牌塔基路1568号",
        "ORG_PROFIE": "    苏州恒铭达电子科技股份有限公司成立于2011年7月,2019年2月登陆深圳证券交易所,股票代码002947。主要从事消费电子功能性器件、消费电子防护产品、精密结构件、精密钣金、EMS总装、自动化设备、物联网设备的设计、研发、生产与销售,产品广泛应用于手机、平板电脑、笔记本电脑、智能穿戴设备、5G基站等。公司具备领先的技术优势、深厚的生产经验、创新的生产工艺、高精密与高品质的产品及快速响应能力,是一家为客户提供一体化综合解决方案的高新技术企业。",
        "MAIN_BUSINESS": "消费电子、通信和新能源等领域的功能性器件、防护产品和精密结构件等的设计、研发、生产和销售",
        "STR_CODEB": null,
        "STR_NAMEB": null,
        "STR_CODEA": "002947.SZ",
        "STR_NAMEA": "恒铭达",
        "SECURITY_CODE_TYPE": 1,
        "SECURITY_TYPE_CODE": "058001001",
        "IS_INNOVATION": 0,
        "SECURITY_PINYIN": "HMD",
        "LISTING_DATE": "2019-02-01 00:00:00",
        "TRADE_MARKET": "深交所主板",
        "TRADE_MARKET_CODE": "069001002001",
        "SECURITY_INNER_CODE": "1001117733",
        "ORG_CODE": "10726859",
        "LISTING_STATE": "0",
        "SECURITY_TYPE": "A股",
        "ORG_TYPE": "通用",
        "CODE_TYPE": "ABStock",
        "ORG_TYPE_CODE": "4",
        "CURRENCY": "CNY",
        "ACCOUNT_FIRM": "致同会计师事务所(特殊普通合伙)",
        "LEGAL_ADVISER": "北京市中伦律师事务所",
        "EXPAND_NAME_ABBR": null,
        "EXPAND_NAME_ABBRN": null,
        "ORG_PROFILE": "领先的消费电子功能性器件供应商，技术创新和高精密制造领域的佼佼者。",
        "SECUCODE_N": "002947.SZ",
        "CORRECODE": "002947",
        "CORRECODE_INNER_CODE": "1001117733",
        "SWINDUSTRY_CODE2": null,
        "SWINDUSTRY_NAME2": null,
        "CSRC_INDUSTRY_NAME": "制造业-计算机、通信和其他电子设备制造业",
        "BOARD_CODE_BK_1LEVEL": "BK1201",
        "BOARD_NAME_1LEVEL": "电子",
        "BOARD_CODE_BK_2LEVEL": "BK1037",
        "BOARD_NAME_2LEVEL": "消费电子",
        "BOARD_CODE_BK_3LEVEL": "BK1338",
        "BOARD_NAME_3LEVEL": "消费电子零部件及组装",
        "BLGAINIAN_CODE": "BK0666,BK0714,BK0722,BK0854,BK0893,BK0922,BK1646,BK1650,BK0520,BK0567,BK0596,BK0804,BK1005,BK1633,BK1643,BK1667",
        "ORG_FORM": "大型民企",
        "ISSUE_PRICE": 18.72,
        "IS_JUMP_CHAIRMAN": "1",
        "IS_JUMP_LEGALPERSON": "0",
        "IS_JUMP_PRESIDENT": "0",
        "IS_JUMP_SECRETARY": "0",
        "CONTROL_HOLDER": "荆世平",
        "CONTROL_HOLDER_CODE": "荆世平",
        "IS_JUMP_CONTROL": "1",
        "CONTROL_DIRECT_RATIO": "23.5%",
        "CONTROL_INDIRECT_RATIO": "0.67%",
        "REAL_CONTROLER": "荆世平、夏琛、荆京平、荆江、荆天平",
        "REAL_CONTROLER_CODE": "荆世平、夏琛、荆京平、荆江、荆天平",
        "IS_JUMP_REAL": "1、1、1、0、0",
        "REAL_DIRECT_RATIO": "23.5%、3.17%、2.26%、0.71%、--",
        "REAL_INDIRECT_RATIO": "0.67%、3.17%、2.26%、--、--",
        "MAX_DATE": "2026-03-31 00:00:00",
        "MAXPROFIT_PRODUCT": "精密柔性结构件",
        "GROSS_PROFIT_RATIO": 92.73,
        "INCOME_STRU_NAME": "精密柔性结构件、精密金属结构件、其他业务",
        "INCOME_STRU_RATIO": "83.81%、14.91%、1.28%",
        "ADD_BUSINESS": null,
        "ADD_BUSINESS_RATIO": null,
        "PRODUCT_NAME": "电子精密结构件、电子精密结构件",
        "AREA_BOARD_NAME": "江苏板块",
        "AREA_BOARD_CODE": "BK0159",
        "PRODUCT_CODE": "PRD000027L1N、PRD000027L1N",
        "IS_USE": "1",
        "INCOME_STRU_NAMENEW": "精密柔性结构件；精密金属结构件；其他业务",
        "INCOME_STRU_RATIONEW": "83.81%；14.91%；1.28%",
        "ORG_NAME_EN": "Suzhou Hengmingda Electronic Technology Co., Ltd.",
        "TRADE_MARKET_ZF": "深圳证券交易所",
        "SECPRESENT": "王昊璐",
        "INDEDIRECTORS": "胡建华,郑凯,毛基业,何蔚宏",
        "PROVINCE": "江苏",
        "ADDRESS_POSTCODE": "215312",
        "REG_NUM": "913205835794960677",
        "BUSINESS_SCOPE": "电子材料及器件、绝缘材料及器件、光学材料及器件、纳米材料及器件、精密结构件、纸制品的研发、设计、加工、生产、销售;货物及技术的进出口业务;包装装潢印刷品印刷(按《印刷许可证》核定范围核定类别经营)(前述经营项目中法律、行政法规规定前置许可经营、限制经营、禁止经营的除外)(依法须经批准的项目,经相关部门批准后方可开展经营活动)一般项目:电子产品销售;新材料技术研发;高性能密封材料销售;五金产品研发;五金产品制造;五金产品批发;五金产品零售;塑料制品制造;塑料制品销售;模具制造;模具销售;合成材料销售;橡胶制品制造;橡胶制品销售;石墨及碳素制品销售;密封件制造;密封件销售;海绵制品制造;海绵制品销售;新型膜材料销售;智能基础制造装备制造;智能基础制造装备销售;智能控制系统集成;电子元器件与机电组件设备销售;汽车零部件及配件制造;汽车零部件研发;通用设备制造(不含特种设备制造);专用设备制造(不含许可类专业设备制造)(除依法须经批准的项目外,凭营业执照依法自主开展经营活动)。",
        "EXPAND_NAME_PINYIN": null,
        "HOST_BROKER": null,
        "TRANSFER_WAY": null,
        "MARKETING_START_DATE": null,
        "MARKET_MAKER": null,
        "TRADE_MARKET_TYPE": null,
        "ORG_FAX": "0512-36828275"
      }
    ],
    "count": 1
  },
  "success": true,
  "message": "ok",
  "code": 0
}