{
  "version": "c56462c9e6eec2bc235a60b5f4f1bc7e",
  "result": {
    "pages": 3,
    "data": [
      {
        "SECUCODE": "605116.SH",
        "SECURITY_CODE": "605116",
        "SECURITY_NAME_ABBR": "奥锐特",
        "ORG_CODE": "10000015507",
        "ORG_TYPE": "通用",
        "REPORT_DATE": "2026-03-31 00:00:00",
        "REPORT_TYPE": "一季报",
        "REPORT_DATE_NAME": "2026一季报",
        "SECURITY_TYPE_CODE": "058001001",
        "NOTICE_DATE": "2026-04-24 00:00:00",
        "UPDATE_DATE": "2026-04-24 00:00:00",
        "CURRENCY": "CNY",
        "EPSJB": 0.16,
        "EPSKCJB": null,
        "EPSXS": 0.16,
        "BPS": 6.645810018835,
        "MGZBGJ": 1.511296117407,
        "MGWFPLR": 3.685534086988,
        "MGJYXJJE": 0.217225753218,
        "TOTALOPERATEREVE": 389262537.93,
        "MLR": 207823614.3,
        "PARENTNETPROFIT": 63926923.65,
        "KCFJCXSYJLR": 58568162.17,
        "TOTALOPERATEREVETZ": -3.167383693751,
        "PARENTNETPROFITTZ": -46.467781767057,
        "KCFJCXSYJLRTZ": -48.163827134537,
        "YYZSRGDHBZC": -0.750097257891,
        "NETPROFITRPHBZC": -12.352959719845,
        "KFJLRGDHBZC": -12.461222794882,
        "ROEJQ": 2.38,
        "ROEKCJQ": null,
        "ZZCJLL": 1.5084292174,
        "XSJLL": 16.4225727937,
        "XSMLL": 53.3890611219,
        "YSZKYYSR": null,
        "XSJXLYYSR": 0.733726410969,
        "JYXJLYYSR": 0.226668251764,
        "TAXRATE": 17.1283705279,
        "LD": 4.221741558106,
        "SD": 2.843380321665,
        "XJLLB": 0.183825466991,
        "ZCFZL": 36.0972954067,
        "QYCS": 1.564878992782,
        "CQBL": 0.564878992781,
        "ZZCZZTS": 979.848132307174,
        "CHZZTS": 324.0282523235,
        "YSZKZZTS": 97.895372704709,
        "TOAZZL": 0.091850968566,
        "CHZZL": 0.277753558076,
        "YSZKZZL": 0.919348867198,
        "TOTALDEPOSITS": null,
        "GROSSLOANS": null,
        "LTDRR": null,
        "NEWCAPITALADER": null,
        "HXYJBCZL": null,
        "NONPERLOAN": null,
        "BLDKBBL": null,
        "NZBJE": null,
        "TOTAL_ROI": null,
        "NET_ROI": null,
        "EARNED_PREMIUM": null,
        "COMPENSATE_EXPENSE": null,
        "SURRENDER_RATE_LIFE": null,
        "SOLVENCY_AR": null,
        "JZB": null,
        "JZC": null,
        "JZBJZC": null,
        "ZYGPGMJZC": null,
        "ZYGDSYLZQJZB": null,
        "YYFXZB": null,
        "JJYWFXZB": null,
        "ZQZYYWFXZB": null,
        "ZQCXYWFXZB": null,
        "RZRQYWFXZB": null,
        "EPSJBTZ": -46.666666666667,
        "BPSTZ": 11.4761005989,
        "MGZBGJTZ": 0.820657107362,
        "MGWFPLRTZ": 20.51295067116,
        "MGJYXJJETZ": 243.256748079457,
        "ROEJQTZ": -52.1126760563,
        "ZZCJLLTZ": -50.898223906413,
        "ZCFZLTZ": -3.415329200481,
        "REPORT_YEAR": "2026",
        "ROIC": 1.933030754543,
        "ROICTZ": -48.407867717546,
        "NBV_LIFE": null,
        "NBV_RATE": null,
        "NHJZ_CURRENT_AMT": null,
        "TOTAL_ASSETS_PK": 4253966607.25,
        "OPERATE_INCOME_PK": 389262537.93,
        "OPERATE_PROFIT_PK": 77129628.51,
        "NETCASH_OPERATE_PK": 88233458.95,
        "NETCASH_INVEST_PK": -175392837.97,
        "NETCASH_FINANCE_PK": 27200539.76,
        "SALE_ER_PK": 35.4843540775,
        "RE_RATIO_PK": 9.684702622676,
        "OI_YOYRATIO_PK": -3.1673836938,
        "TA_YOYRATIO_PK": 9.1586848414,
        "EQUITY_YOYRATIO_PK": 11.3835351128,
        "TOTAL_EQUITY_PK": 2718399714.53,
        "TOTAL_SHARE": 406183234,
        "A_FREE_SHARE": 406183234,
        "B_FREE_SHARE": null,
        "DJD_TOI_YOY": -3.167383693751,
        "DJD_DPNP_YOY": -46.467781767057,
        "DJD_DEDUCTDPNP_YOY": -48.163827134537,
        "DJD_TOI_QOQ": -15.455812571253,
        "DJD_DPNP_QOQ": -33.179358696996,
        "DJD_DEDUCTDPNP_QOQ": -38.15171192365,
        "XSMLL_TB": -12.093012180561,
        "PER_TOI": 0.958342209492,
        "PER_OI": 0.958342209492,
        "PER_EBIT": 0.20733203269,
        "STAFF_NUM": null,
        "AVG_TOI": null,
        "AVG_NET_PROFIT": null,
        "PREPAID_ACCOUNTS_RATIO": 19.069402050096,
        "ACCOUNTS_PAYABLE_TR": 0.638002926598,
        "FIXED_ASSET_TR": 0.255203797228,
        "CURRENT_ASSET_TR": 0.190676114556,
        "PREPAID_ACCOUNTS_TDAYS": 4.719602626426,
        "INVENTORY_TR_YOY": 5.976734942855,
        "PAYABLE_TDAYS": 141.065183634664,
        "OPERATE_CYCLE": 421.874658599051,
        "GUARD_SPEED_RATIO": 2.790548472777,
        "CASH_RATIO": 1.910836918165,
        "INTEREST_COVERAGE_RATIO": null,
        "CA_TA": 47.6348930111,
        "NCA_TA": 52.3651069889,
        "LIQUIDATION_RATIO": 265.116776440707,
        "INTEREST_DEBT_RATIO": 23.363645985,
        "FC_LIABILITIES": 143.527188740309,
        "FCFF_FORWARD": -155249759.926283,
        "FCFF_BACK": -50947675.9611175,
        "SS_OI": 1.054226445171,
        "SS_TA": 0.09646781451,
        "NCO_OP": 1.143963229883,
        "NCO_NETPROFIT": 1.380223760384,
        "NCO_FIXED": 0.058429483964,
        "FIRST_ADEQUACY_RATIO": null,
        "NET_INTEREST_SPREAD": null,
        "NET_INTEREST_MARGIN": null,
        "LOAN_ADVANCES": null,
        "NON_PERFORMING_LOAN": null,
        "OVERDUE_LOANS": null,
        "LOAN_PROVISION_RATIO": null,
        "REVENUE_RATIO": null,
        "LIABILITY": 1535566892.72,
        "CAPITAL_PROVISIONS_SUM": null,
        "RISK_COVERAGE": null,
        "CAPITAL_LEVERAGE_RATIO": null,
        "LIQUIDITY_COVERAGE_RATIO": null,
        "NET_FUNDING_RATIO": null,
        "NET_CAPITAL_LIABILITIES": null,
        "NET_ASSETS_LIABILITIES": null,
        "PROPRIETARY_CAPITAL": null,
        "IS_BZ": "0",
        "RDPERSONNEL": null,
        "PRATIO": null,
        "RDEXPEND": null,
        "RCAPITAL_RATIO": null,
        "RCOST_RATIO": null,
        "TOTALOPER_RATIO": null,
        "INTSTCOVRATE": 9.421303667867,
        "CL_TL": 31.2578344659
      },
      {
        "SECUCODE": "605116.SH",
        "SECURITY_CODE": "605116",
        "SECURITY_NAME_ABBR": "奥锐特",
        "ORG_CODE": "10000015507",
        "ORG_TYPE": "通用",
        "REPORT_DATE": "2025-12-31 00:00:00",
        "REPORT_TYPE": "年报",
        "REPORT_DATE_NAME": "2025年报",
        "SECURITY_TYPE_CODE": "058001001",
        "NOTICE_DATE": "2026-04-17 00:00:00",
        "UPDATE_DATE": "2026-04-17 00:00:00",
        "CURRENCY": "CNY",
        "EPSJB": 1.12,
        "EPSKCJB": 1.09,
        "EPSXS": 1.1,
        "BPS": 6.495838092748,
        "MGZBGJ": 1.511492352247,
        "MGWFPLR": 3.528045409858,
        "MGJYXJJE": 1.037669373812,
        "TOTALOPERATEREVE": 1697477562.55,
        "MLR": 1012835386.11,
        "PARENTNETPROFIT": 449210068.02,
        "KCFJCXSYJLR": 436705835.26,
        "TOTALOPERATEREVETZ": 15.025436216157,
        "PARENTNETPROFITTZ": 26.61221960679,
        "KCFJCXSYJLRTZ": 24.429538197191,
        "YYZSRGDHBZC": 4.494159654453,
        "NETPROFITRPHBZC": 5.811588060001,
        "KFJLRGDHBZC": 6.150138946755,
        "ROEJQ": 22.05,
        "ROEKCJQ": 21.44,
        "ZZCJLL": 11.0924075598,
        "XSJLL": 26.4633876718,
        "XSMLL": 59.6670853539,
        "YSZKYYSR": null,
        "XSJXLYYSR": 0.545506546036,
        "JYXJLYYSR": 0.248307467155,
        "TAXRATE": 13.329585578,
        "LD": 3.94695511141,
        "SD": 2.709320210141,
        "XJLLB": 0.808921632637,
        "ZCFZL": 37.0543145477,
        "QYCS": 1.588671237456,
        "CQBL": 0.588671237455,
        "ZZCZZTS": 858.859495609079,
        "CHZZTS": 324.590902967012,
        "YSZKZZTS": 82.518927296094,
        "TOAZZL": 0.419160528399,
        "CHZZL": 1.109088383899,
        "YSZKZZL": 4.362635480079,
        "TOTALDEPOSITS": null,
        "GROSSLOANS": null,
        "LTDRR": null,
        "NEWCAPITALADER": null,
        "HXYJBCZL": null,
        "NONPERLOAN": null,
        "BLDKBBL": null,
        "NZBJE": null,
        "TOTAL_ROI": null,
        "NET_ROI": null,
        "EARNED_PREMIUM": null,
        "COMPENSATE_EXPENSE": null,
        "SURRENDER_RATE_LIFE": null,
        "SOLVENCY_AR": null,
        "JZB": null,
        "JZC": null,
        "JZBJZC": null,
        "ZYGPGMJZC": null,
        "ZYGDSYLZQJZB": null,
        "YYFXZB": null,
        "JJYWFXZB": null,
        "ZQZYYWFXZB": null,
        "ZQCXYWFXZB": null,
        "RZRQYWFXZB": null,
        "EPSJBTZ": 25.842696629214,
        "BPSTZ": 14.0984207552,
        "MGZBGJTZ": 1.230521570361,
        "MGWFPLRTZ": 27.632739753699,
        "MGJYXJJETZ": 26.801661947228,
        "ROEJQTZ": 27.0893371758,
        "ZZCJLLTZ": 0.859901679902,
        "ZCFZLTZ": -7.060083077484,
        "REPORT_YEAR": "2025",
        "ROIC": 13.613553799846,
        "ROICTZ": 2.665172811618,
        "NBV_LIFE": null,
        "NBV_RATE": null,
        "NHJZ_CURRENT_AMT": null,
        "TOTAL_ASSETS_PK": 4221992743.16,
        "OPERATE_INCOME_PK": 1697477562.55,
        "OPERATE_PROFIT_PK": 520581543.82,
        "NETCASH_OPERATE_PK": 421496354.11,
        "NETCASH_INVEST_PK": -242188015,
        "NETCASH_FINANCE_PK": -181418090.53,
        "SALE_ER_PK": 28.4368315293,
        "RE_RATIO_PK": 9.036566823868,
        "OI_YOYRATIO_PK": 15.0254362162,
        "TA_YOYRATIO_PK": 8.886582974,
        "EQUITY_YOYRATIO_PK": 13.9836814957,
        "TOTAL_EQUITY_PK": 2657562271.93,
        "TOTAL_SHARE": 406183234,
        "A_FREE_SHARE": 406183234,
        "B_FREE_SHARE": null,
        "DJD_TOI_YOY": 18.844300685767,
        "DJD_DPNP_YOY": 34.751279926528,
        "DJD_DEDUCTDPNP_YOY": 36.460933123608,
        "DJD_TOI_QOQ": 10.922916224768,
        "DJD_DPNP_QOQ": -19.363421615063,
        "DJD_DEDUCTDPNP_QOQ": -18.159625459066,
        "XSMLL_TB": 1.889220151331,
        "PER_TOI": 4.17896966893,
        "PER_OI": 4.17896966893,
        "PER_EBIT": 1.328569891911,
        "STAFF_NUM": 2026,
        "AVG_TOI": 837846.7732231,
        "AVG_NET_PROFIT": 221722.639693978,
        "PREPAID_ACCOUNTS_RATIO": 138.321449302422,
        "ACCOUNTS_PAYABLE_TR": 2.38185430836,
        "FIXED_ASSET_TR": 1.581016138533,
        "CURRENT_ASSET_TR": 0.827352803886,
        "PREPAID_ACCOUNTS_TDAYS": 2.60263322728,
        "INVENTORY_TR_YOY": -0.294767768686,
        "PAYABLE_TDAYS": 151.142745690384,
        "OPERATE_CYCLE": 407.107101785741,
        "GUARD_SPEED_RATIO": 2.660632474902,
        "CASH_RATIO": 1.830684161203,
        "INTEREST_COVERAGE_RATIO": 12.142367846758,
        "CA_TA": 48.7115643956,
        "NCA_TA": 51.2884356044,
        "LIQUIDATION_RATIO": 258.182445383102,
        "INTEREST_DEBT_RATIO": 23.1251663846,
        "FC_LIABILITIES": 152.069810328254,
        "FCFF_FORWARD": 238578158.492449,
        "FCFF_BACK": 225174043.98589,
        "SS_OI": 0.964829271634,
        "SS_TA": 0.387915408652,
        "NCO_OP": 0.809664420711,
        "NCO_NETPROFIT": 0.938305670592,
        "NCO_FIXED": 0.273607087582,
        "FIRST_ADEQUACY_RATIO": null,
        "NET_INTEREST_SPREAD": null,
        "NET_INTEREST_MARGIN": null,
        "LOAN_ADVANCES": null,
        "NON_PERFORMING_LOAN": null,
        "OVERDUE_LOANS": null,
        "LOAN_PROVISION_RATIO": null,
        "REVENUE_RATIO": null,
        "LIABILITY": 1564430471.23,
        "CAPITAL_PROVISIONS_SUM": null,
        "RISK_COVERAGE": null,
        "CAPITAL_LEVERAGE_RATIO": null,
        "LIQUIDITY_COVERAGE_RATIO": null,
        "NET_FUNDING_RATIO": null,
        "NET_CAPITAL_LIABILITIES": null,
        "NET_ASSETS_LIABILITIES": null,
        "PROPRIETARY_CAPITAL": null,
        "IS_BZ": "0",
        "RDPERSONNEL": 303,
        "PRATIO": 14.96,
        "RDEXPEND": 153393694.26,
        "RCAPITAL_RATIO": 0,
        "RCOST_RATIO": 100,
        "TOTALOPER_RATIO": 1106.61495620074,
        "INTSTCOVRATE": 15.930975103796,
        "CL_TL": 33.3066617336
      },
      {
        "SECUCODE": "605116.SH",
        "SECURITY_CODE": "605116",
        "SECURITY_NAME_ABBR": "奥锐特",
        "ORG_CODE": "10000015507",
        "ORG_TYPE": "通用",
        "REPORT_DATE": "2025-09-30 00:00:00",
        "REPORT_TYPE": "三季报",
        "REPORT_DATE_NAME": "2025三季报",
        "SECURITY_TYPE_CODE": "058001001",
        "NOTICE_DATE": "2025-10-31 00:00:00",
        "UPDATE_DATE": "2025-10-31 00:00:00",
        "CURRENCY": "CNY",
        "EPSJB": 0.87,
        "EPSKCJB": null,
        "EPSXS": 0.87,
        "BPS": 6.209317254225,
        "MGZBGJ": 1.51072292766,
        "MGWFPLR": 3.345557802163,
        "MGJYXJJE": 0.865268936169,
        "TOTALOPERATEREVE": 1237052606.36,
        "MLR": 753647043.71,
        "PARENTNETPROFIT": 353540642.52,
        "KCFJCXSYJLR": 342009338.41,
        "TOTALOPERATEREVETZ": 13.666005213663,
        "PARENTNETPROFITTZ": 24.576069406979,
        "KCFJCXSYJLRTZ": 21.464348917466,
        "YYZSRGDHBZC": 3.664214130692,
        "NETPROFITRPHBZC": 5.843911768632,
        "KFJLRGDHBZC": 5.446618471181,
        "ROEJQ": 14.37,
        "ROEKCJQ": null,
        "ZZCJLL": 8.8994351921,
        "XSJLL": 28.5792730804,
        "XSMLL": 60.9227966406,
        "YSZKYYSR": null,
        "XSJXLYYSR": 0.606419458262,
        "JYXJLYYSR": 0.284117357817,
        "TAXRATE": 12.5065304495,
        "LD": 4.300678634382,
        "SD": 3.01446240406,
        "XJLLB": 0.725642205654,
        "ZCFZL": 37.5296401522,
        "QYCS": 1.600759147916,
        "CQBL": 0.600759147917,
        "ZZCZZTS": 867.066680658086,
        "CHZZTS": 338.670904933107,
        "YSZKZZTS": 80.892272996043,
        "TOAZZL": 0.311394735864,
        "CHZZL": 0.797234117449,
        "YSZKZZL": 3.33777244723,
        "TOTALDEPOSITS": null,
        "GROSSLOANS": null,
        "LTDRR": null,
        "NEWCAPITALADER": null,
        "HXYJBCZL": null,
        "NONPERLOAN": null,
        "BLDKBBL": null,
        "NZBJE": null,
        "TOTAL_ROI": null,
        "NET_ROI": null,
        "EARNED_PREMIUM": null,
        "COMPENSATE_EXPENSE": null,
        "SURRENDER_RATE_LIFE": null,
        "SOLVENCY_AR": null,
        "JZB": null,
        "JZC": null,
        "JZBJZC": null,
        "ZYGPGMJZC": null,
        "ZYGDSYLZQJZB": null,
        "YYFXZB": null,
        "JJYWFXZB": null,
        "ZQZYYWFXZB": null,
        "ZQCXYWFXZB": null,
        "RZRQYWFXZB": null,
        "EPSJBTZ": 24.285714285714,
        "BPSTZ": 15.658028009,
        "MGZBGJTZ": 2.103573153724,
        "MGWFPLRTZ": 26.280945243539,
        "MGJYXJJETZ": 16.578602885584,
        "ROEJQTZ": 4.5090909091,
        "ZZCJLLTZ": -1.760693386287,
        "ZCFZLTZ": -2.637209622159,
        "REPORT_YEAR": "2025",
        "ROIC": 10.777448282357,
        "ROICTZ": 1.49133155017,
        "NBV_LIFE": null,
        "NBV_RATE": null,
        "NHJZ_CURRENT_AMT": null,
        "TOTAL_ASSETS_PK": 4067815371.39,
        "OPERATE_INCOME_PK": 1237052606.36,
        "OPERATE_PROFIT_PK": 404697773.98,
        "NETCASH_OPERATE_PK": 351468118,
        "NETCASH_INVEST_PK": -367575670.42,
        "NETCASH_FINANCE_PK": -136194267.48,
        "SALE_ER_PK": 28.6714000946,
        "RE_RATIO_PK": 9.170275692139,
        "OI_YOYRATIO_PK": 13.6660052137,
        "TA_YOYRATIO_PK": 10.2115461519,
        "EQUITY_YOYRATIO_PK": 12.0346200702,
        "TOTAL_EQUITY_PK": 2541178900.45,
        "TOTAL_SHARE": 406183234,
        "A_FREE_SHARE": 406183234,
        "B_FREE_SHARE": null,
        "DJD_TOI_YOY": 16.054141090611,
        "DJD_DPNP_YOY": 24.620893046815,
        "DJD_DEDUCTDPNP_YOY": 22.496826449624,
        "DJD_TOI_QOQ": -1.163485000318,
        "DJD_DPNP_QOQ": 2.738518944442,
        "DJD_DEDUCTDPNP_QOQ": 2.113839500935,
        "XSMLL_TB": 4.637190644601,
        "PER_TOI": 3.045463124169,
        "PER_OI": 3.045463124169,
        "PER_EBIT": 1.028078488902,
        "STAFF_NUM": null,
        "AVG_TOI": null,
        "AVG_NET_PROFIT": null,
        "PREPAID_ACCOUNTS_RATIO": 90.7346669628,
        "ACCOUNTS_PAYABLE_TR": 1.837291670808,
        "FIXED_ASSET_TR": 1.310869798102,
        "CURRENT_ASSET_TR": 0.599078804607,
        "PREPAID_ACCOUNTS_TDAYS": 2.975709384713,
        "INVENTORY_TR_YOY": -4.325910171031,
        "PAYABLE_TDAYS": 146.955436793147,
        "OPERATE_CYCLE": 419.577004145102,
        "GUARD_SPEED_RATIO": 2.961068552659,
        "CASH_RATIO": 2.148896659799,
        "INTEREST_COVERAGE_RATIO": null,
        "CA_TA": 51.2081586198,
        "NCA_TA": 48.7918413802,
        "LIQUIDATION_RATIO": 254.734839825718,
        "INTEREST_DEBT_RATIO": 24.3658357631,
        "FC_LIABILITIES": 127.300622390255,
        "FCFF_FORWARD": -147464421.570354,
        "FCFF_BACK": 39949243.8986066,
        "SS_OI": 0.962334068236,
        "SS_TA": 0.292652875957,
        "NCO_OP": 0.868470598549,
        "NCO_NETPROFIT": 0.994137804058,
        "NCO_FIXED": 0.274462472328,
        "FIRST_ADEQUACY_RATIO": null,
        "NET_INTEREST_SPREAD": null,
        "NET_INTEREST_MARGIN": null,
        "LOAN_ADVANCES": null,
        "NON_PERFORMING_LOAN": null,
        "OVERDUE_LOANS": null,
        "LOAN_PROVISION_RATIO": null,
        "REVENUE_RATIO": null,
        "LIABILITY": 1526636470.94,
        "CAPITAL_PROVISIONS_SUM": null,
        "RISK_COVERAGE": null,
        "CAPITAL_LEVERAGE_RATIO": null,
        "LIQUIDITY_COVERAGE_RATIO": null,
        "NET_FUNDING_RATIO": null,
        "NET_CAPITAL_LIABILITIES": null,
        "NET_ASSETS_LIABILITIES": null,
        "PROPRIETARY_CAPITAL": null,
        "IS_BZ": "0",
        "RDPERSONNEL": null,
        "PRATIO": null,
        "RDEXPEND": null,
        "RCAPITAL_RATIO": null,
        "RCOST_RATIO": null,
        "TOTALOPER_RATIO": null,
        "INTSTCOVRATE": 16.840373677538,
        "CL_TL": 31.7269093553
      },
      {
        "SECUCODE": "605116.SH",
        "SECURITY_CODE": "605116",
        "SECURITY_NAME_ABBR": "奥锐特",
        "ORG_CODE": "10000015507",
        "ORG_TYPE": "通用",
        "REPORT_DATE": "2025-06-30 00:00:00",
        "REPORT_TYPE": "中报",
        "REPORT_DATE_NAME": "2025中报",
        "SECURITY_TYPE_CODE": "058001001",
        "NOTICE_DATE": "2025-08-29 00:00:00",
        "UPDATE_DATE": "2025-08-29 00:00:00",
        "CURRENCY": "CNY",
        "EPSJB": 0.58,
        "EPSKCJB": 0.56,
        "EPSXS": 0.58,
        "BPS": 5.933767226919,
        "MGZBGJ": 1.504861111837,
        "MGWFPLR": 3.053474821864,
        "MGJYXJJE": 0.530188451743,
        "TOTALOPERATEREVE": 821967093.05,
        "MLR": 494084941.07,
        "PARENTNETPROFIT": 234897927.99,
        "KCFJCXSYJLR": 226300560.95,
        "TOTALOPERATEREVETZ": 12.496983936394,
        "PARENTNETPROFITTZ": 24.553442047145,
        "KCFJCXSYJLRTZ": 20.943133010476,
        "YYZSRGDHBZC": 1.617129930604,
        "NETPROFITRPHBZC": 2.314226131548,
        "KFJLRGDHBZC": 2.191841629065,
        "ROEJQ": 9.59,
        "ROEKCJQ": 9.24,
        "ZZCJLL": 6.0385614236,
        "XSJLL": 28.5775343047,
        "XSMLL": 60.1100634378,
        "YSZKYYSR": null,
        "XSJXLYYSR": 0.627857528292,
        "JYXJLYYSR": 0.262005649668,
        "TAXRATE": 12.2075519059,
        "LD": 4.507809257254,
        "SD": 3.152852975938,
        "XJLLB": 0.482360602828,
        "ZCFZL": 37.7515180186,
        "QYCS": 1.606464877808,
        "CQBL": 0.606464877807,
        "ZZCZZTS": 851.851262909758,
        "CHZZTS": 327.923789949067,
        "YSZKZZTS": 77.219295261186,
        "TOAZZL": 0.211304493915,
        "CHZZL": 0.548908025331,
        "YSZKZZL": 2.331023604802,
        "TOTALDEPOSITS": null,
        "GROSSLOANS": null,
        "LTDRR": null,
        "NEWCAPITALADER": null,
        "HXYJBCZL": null,
        "NONPERLOAN": null,
        "BLDKBBL": null,
        "NZBJE": null,
        "TOTAL_ROI": null,
        "NET_ROI": null,
        "EARNED_PREMIUM": null,
        "COMPENSATE_EXPENSE": null,
        "SURRENDER_RATE_LIFE": null,
        "SOLVENCY_AR": null,
        "JZB": null,
        "JZC": null,
        "JZBJZC": null,
        "ZYGPGMJZC": null,
        "ZYGDSYLZQJZB": null,
        "YYFXZB": null,
        "JJYWFXZB": null,
        "ZQZYYWFXZB": null,
        "ZQCXYWFXZB": null,
        "RZRQYWFXZB": null,
        "EPSJBTZ": 26.086956521739,
        "BPSTZ": 15.8866459391,
        "MGZBGJTZ": 2.62216773628,
        "MGWFPLRTZ": 26.442066711438,
        "MGJYXJJETZ": 28.710329483476,
        "ROEJQTZ": 3.5637149028,
        "ZZCJLLTZ": -12.84213994155,
        "ZCFZLTZ": 37.185192075927,
        "REPORT_YEAR": "2025",
        "ROIC": 7.32853434217,
        "ROICTZ": -10.889698360829,
        "NBV_LIFE": null,
        "NBV_RATE": null,
        "NHJZ_CURRENT_AMT": null,
        "TOTAL_ASSETS_PK": 3902507684.21,
        "OPERATE_INCOME_PK": 821967093.05,
        "OPERATE_PROFIT_PK": 267668999.07,
        "NETCASH_OPERATE_PK": 215360022.22,
        "NETCASH_INVEST_PK": 1399588.5,
        "NETCASH_FINANCE_PK": -129000685.73,
        "SALE_ER_PK": 28.1180092213,
        "RE_RATIO_PK": 8.735369755932,
        "OI_YOYRATIO_PK": 12.4969839364,
        "TA_YOYRATIO_PK": 35.9998197219,
        "EQUITY_YOYRATIO_PK": 16.7994631269,
        "TOTAL_EQUITY_PK": 2429251792.63,
        "TOTAL_SHARE": 406183234,
        "A_FREE_SHARE": 406183234,
        "B_FREE_SHARE": null,
        "DJD_TOI_YOY": 6.312869988997,
        "DJD_DPNP_YOY": 8.52601768947,
        "DJD_DEDUCTDPNP_YOY": 7.973801288765,
        "DJD_TOI_QOQ": 4.471831686991,
        "DJD_DPNP_QOQ": -3.29716454881,
        "DJD_DEDUCTDPNP_QOQ": 0.288937919999,
        "XSMLL_TB": 5.420304683507,
        "PER_TOI": 2.023576409195,
        "PER_OI": 2.023576409195,
        "PER_EBIT": 0.683880683371,
        "STAFF_NUM": null,
        "AVG_TOI": null,
        "AVG_NET_PROFIT": null,
        "PREPAID_ACCOUNTS_RATIO": 84.22104788356,
        "ACCOUNTS_PAYABLE_TR": 1.280870921828,
        "FIXED_ASSET_TR": 1.033493309469,
        "CURRENT_ASSET_TR": 0.404969533824,
        "PREPAID_ACCOUNTS_TDAYS": 2.137232966382,
        "INVENTORY_TR_YOY": -7.022437474904,
        "PAYABLE_TDAYS": 140.529382728989,
        "OPERATE_CYCLE": 405.148661661687,
        "GUARD_SPEED_RATIO": 3.085197129898,
        "CASH_RATIO": 2.282657705456,
        "INTEREST_COVERAGE_RATIO": 12.9224664639,
        "CA_TA": 51.5721244879,
        "NCA_TA": 48.4278755121,
        "LIQUIDATION_RATIO": 252.942407132919,
        "INTEREST_DEBT_RATIO": 25.1380215898,
        "FC_LIABILITIES": 192.589513167191,
        "FCFF_FORWARD": 162326288.240172,
        "FCFF_BACK": 98747392.4968951,
        "SS_OI": 1.002337610661,
        "SS_TA": 0.211117721926,
        "NCO_OP": 0.804575886518,
        "NCO_NETPROFIT": 0.91682384797,
        "NCO_FIXED": 0.218895188369,
        "FIRST_ADEQUACY_RATIO": null,
        "NET_INTEREST_SPREAD": null,
        "NET_INTEREST_MARGIN": null,
        "LOAN_ADVANCES": null,
        "NON_PERFORMING_LOAN": null,
        "OVERDUE_LOANS": null,
        "LOAN_PROVISION_RATIO": null,
        "REVENUE_RATIO": null,
        "LIABILITY": 1473255891.58,
        "CAPITAL_PROVISIONS_SUM": null,
        "RISK_COVERAGE": null,
        "CAPITAL_LEVERAGE_RATIO": null,
        "LIQUIDITY_COVERAGE_RATIO": null,
        "NET_FUNDING_RATIO": null,
        "NET_CAPITAL_LIABILITIES": null,
        "NET_ASSETS_LIABILITIES": null,
        "PROPRIETARY_CAPITAL": null,
        "IS_BZ": "0",
        "RDPERSONNEL": null,
        "PRATIO": null,
        "RDEXPEND": 71801864.85,
        "RCAPITAL_RATIO": null,
        "RCOST_RATIO": null,
        "TOTALOPER_RATIO": 1144.77123228924,
        "INTSTCOVRATE": 17.054705846036,
        "CL_TL": 30.3050546542
      },
      {
        "SECUCODE": "605116.SH",
        "SECURITY_CODE": "605116",
        "SECURITY_NAME_ABBR": "奥锐特",
        "ORG_CODE": "10000015507",
        "ORG_TYPE": "通用",
        "REPORT_DATE": "2025-03-31 00:00:00",
        "REPORT_TYPE": "一季报",
        "REPORT_DATE_NAME": "2025一季报",
        "SECURITY_TYPE_CODE": "058001001",
        "NOTICE_DATE": "2025-04-26 00:00:00",
        "UPDATE_DATE": "2026-04-24 00:00:00",
        "CURRENCY": "CNY",
        "EPSJB": 0.3,
        "EPSKCJB": null,
        "EPSXS": 0.3,
        "BPS": 5.961645575265,
        "MGZBGJ": 1.498994512402,
        "MGWFPLR": 3.058205833035,
        "MGJYXJJE": 0.063283753177,
        "TOTALOPERATEREVE": 401995270.58,
        "MLR": 244146120.85,
        "PARENTNETPROFIT": 119417662.41,
        "KCFJCXSYJLR": 112987049.26,
        "TOTALOPERATEREVETZ": 19.775785464175,
        "PARENTNETPROFITTZ": 45.304940265392,
        "KCFJCXSYJLRTZ": 37.507663994898,
        "YYZSRGDHBZC": 4.497544868693,
        "NETPROFITRPHBZC": 10.494454971542,
        "KFJLRGDHBZC": 8.781248627906,
        "ROEJQ": 4.97,
        "ROEKCJQ": null,
        "ZZCJLL": 3.0720461405,
        "XSJLL": 29.7062356574,
        "XSMLL": 60.733580397,
        "YSZKYYSR": null,
        "XSJXLYYSR": 0.440247152945,
        "JYXJLYYSR": 0.063944928737,
        "TAXRATE": 15.6271729533,
        "LD": 4.618407745913,
        "SD": 3.214297344255,
        "XJLLB": 0.058705384862,
        "ZCFZL": 37.3737313674,
        "QYCS": 1.596774040406,
        "CQBL": 0.596774040406,
        "ZZCZZTS": 870.286801339209,
        "CHZZTS": 343.394562104842,
        "YSZKZZTS": 83.155840765381,
        "TOAZZL": 0.103414184682,
        "CHZZL": 0.262089182334,
        "YSZKZZL": 1.08230521358,
        "TOTALDEPOSITS": null,
        "GROSSLOANS": null,
        "LTDRR": null,
        "NEWCAPITALADER": null,
        "HXYJBCZL": null,
        "NONPERLOAN": null,
        "BLDKBBL": null,
        "NZBJE": null,
        "TOTAL_ROI": null,
        "NET_ROI": null,
        "EARNED_PREMIUM": null,
        "COMPENSATE_EXPENSE": null,
        "SURRENDER_RATE_LIFE": null,
        "SOLVENCY_AR": null,
        "JZB": null,
        "JZC": null,
        "JZBJZC": null,
        "ZYGPGMJZC": null,
        "ZYGDSYLZQJZB": null,
        "YYFXZB": null,
        "JJYWFXZB": null,
        "ZQZYYWFXZB": null,
        "ZQCXYWFXZB": null,
        "RZRQYWFXZB": null,
        "EPSJBTZ": 50,
        "BPSTZ": 17.7000585085,
        "MGZBGJTZ": 3.149846436036,
        "MGWFPLRTZ": 28.877399975033,
        "MGJYXJJETZ": -71.255247193142,
        "ROEJQTZ": 58.2802547771,
        "ZZCJLLTZ": -1.657308839041,
        "ZCFZLTZ": 59.477071579577,
        "REPORT_YEAR": "2025",
        "ROIC": 3.74675491984,
        "ROICTZ": 7.263182248357,
        "NBV_LIFE": null,
        "NBV_RATE": null,
        "NHJZ_CURRENT_AMT": null,
        "TOTAL_ASSETS_PK": 3897048240.76,
        "OPERATE_INCOME_PK": 401995270.58,
        "OPERATE_PROFIT_PK": 141538053.98,
        "NETCASH_OPERATE_PK": 25705558.93,
        "NETCASH_INVEST_PK": -63195900.41,
        "NETCASH_FINANCE_PK": 2976051.25,
        "SALE_ER_PK": 26.3707903272,
        "RE_RATIO_PK": 7.981990448222,
        "OI_YOYRATIO_PK": 19.7757854642,
        "TA_YOYRATIO_PK": 45.0243829529,
        "EQUITY_YOYRATIO_PK": 18.6228272131,
        "TOTAL_EQUITY_PK": 2440575900,
        "TOTAL_SHARE": 406183234,
        "A_FREE_SHARE": 406183234,
        "B_FREE_SHARE": null,
        "DJD_TOI_YOY": 19.775785464175,
        "DJD_DPNP_YOY": 45.304940265392,
        "DJD_DEDUCTDPNP_YOY": 37.507663994898,
        "DJD_TOI_QOQ": 3.762504983224,
        "DJD_DPNP_QOQ": 68.200893561146,
        "DJD_DEDUCTDPNP_QOQ": 62.818252900373,
        "XSMLL_TB": 13.138374919528,
        "PER_TOI": 0.989660234615,
        "PER_OI": 0.989660234615,
        "PER_EBIT": 0.363135316895,
        "STAFF_NUM": null,
        "AVG_TOI": null,
        "AVG_NET_PROFIT": null,
        "PREPAID_ACCOUNTS_RATIO": 45.099133280274,
        "ACCOUNTS_PAYABLE_TR": 0.61718160929,
        "FIXED_ASSET_TR": 0.581207853577,
        "CURRENT_ASSET_TR": 0.197585508427,
        "PREPAID_ACCOUNTS_TDAYS": 1.995603761178,
        "INVENTORY_TR_YOY": -13.703900906191,
        "PAYABLE_TDAYS": 145.824176620452,
        "OPERATE_CYCLE": 426.536630502333,
        "GUARD_SPEED_RATIO": 3.163628713638,
        "CASH_RATIO": 2.256414254807,
        "INTEREST_COVERAGE_RATIO": null,
        "CA_TA": 51.8926205475,
        "NCA_TA": 48.1073794525,
        "LIQUIDATION_RATIO": 255.39273827466,
        "INTEREST_DEBT_RATIO": 24.9696299995,
        "FC_LIABILITIES": 168.222535703207,
        "FCFF_FORWARD": -111983639.265287,
        "FCFF_BACK": -53416790.1313258,
        "SS_OI": 0.877441839057,
        "SS_TA": 0.090511445514,
        "NCO_OP": 0.181615884966,
        "NCO_NETPROFIT": 0.215257595997,
        "NCO_FIXED": 0.033104304683,
        "FIRST_ADEQUACY_RATIO": null,
        "NET_INTEREST_SPREAD": null,
        "NET_INTEREST_MARGIN": null,
        "LOAN_ADVANCES": null,
        "NON_PERFORMING_LOAN": null,
        "OVERDUE_LOANS": null,
        "LOAN_PROVISION_RATIO": null,
        "REVENUE_RATIO": null,
        "LIABILITY": 1456472340.76,
        "CAPITAL_PROVISIONS_SUM": null,
        "RISK_COVERAGE": null,
        "CAPITAL_LEVERAGE_RATIO": null,
        "LIQUIDITY_COVERAGE_RATIO": null,
        "NET_FUNDING_RATIO": null,
        "NET_CAPITAL_LIABILITIES": null,
        "NET_ASSETS_LIABILITIES": null,
        "PROPRIETARY_CAPITAL": null,
        "IS_BZ": "0",
        "RDPERSONNEL": null,
        "PRATIO": null,
        "RDEXPEND": null,
        "RCAPITAL_RATIO": null,
        "RCOST_RATIO": null,
        "TOTALOPER_RATIO": null,
        "INTSTCOVRATE": 18.357320516335,
        "CL_TL": 30.0640074457
      },
      {
        "SECUCODE": "605116.SH",
        "SECURITY_CODE": "605116",
        "SECURITY_NAME_ABBR": "奥锐特",
        "ORG_CODE": "10000015507",
        "ORG_TYPE": "通用",
        "REPORT_DATE": "2024-12-31 00:00:00",
        "REPORT_TYPE": "年报",
        "REPORT_DATE_NAME": "2024年报",
        "SECURITY_TYPE_CODE": "058001001",
        "NOTICE_DATE": "2025-04-26 00:00:00",
        "UPDATE_DATE": "2026-04-17 00:00:00",
        "CURRENCY": "CNY",
        "EPSJB": 0.89,
        "EPSKCJB": 0.88,
        "EPSXS": 0.89,
        "BPS": 5.693188433068,
        "MGZBGJ": 1.493119198439,
        "MGWFPLR": 2.764216623937,
        "MGJYXJJE": 0.818340515319,
        "TOTALOPERATEREVE": 1475741034.67,
        "MLR": 864204929.09,
        "PARENTNETPROFIT": 354792033.04,
        "KCFJCXSYJLR": 350966371.48,
        "TOTALOPERATEREVETZ": 16.887519786336,
        "PARENTNETPROFITTZ": 22.587513355959,
        "KCFJCXSYJLRTZ": 34.251136926852,
        "YYZSRGDHBZC": 3.319710492777,
        "NETPROFITRPHBZC": 4.146078096348,
        "KFJLRGDHBZC": 0.814221701367,
        "ROEJQ": 17.35,
        "ROEKCJQ": 17.16,
        "ZZCJLL": 10.9978369749,
        "XSJLL": 24.0416187329,
        "XSMLL": 58.5607439779,
        "YSZKYYSR": null,
        "XSJXLYYSR": 0.502012826109,
        "JYXJLYYSR": 0.225246718639,
        "TAXRATE": 12.91135185,
        "LD": 3.84709306818,
        "SD": 2.738670325723,
        "XJLLB": 0.624779482272,
        "ZCFZL": 39.8691065956,
        "QYCS": 1.663038653483,
        "CQBL": 0.663038653483,
        "ZZCZZTS": 786.971362060278,
        "CHZZTS": 323.634113604978,
        "YSZKZZTS": 77.692712530033,
        "TOAZZL": 0.457449937006,
        "CHZZL": 1.112367284122,
        "YSZKZZL": 4.63363922145,
        "TOTALDEPOSITS": null,
        "GROSSLOANS": null,
        "LTDRR": null,
        "NEWCAPITALADER": null,
        "HXYJBCZL": null,
        "NONPERLOAN": null,
        "BLDKBBL": null,
        "NZBJE": null,
        "TOTAL_ROI": null,
        "NET_ROI": null,
        "EARNED_PREMIUM": null,
        "COMPENSATE_EXPENSE": null,
        "SURRENDER_RATE_LIFE": null,
        "SOLVENCY_AR": null,
        "JZB": null,
        "JZC": null,
        "JZBJZC": null,
        "ZYGPGMJZC": null,
        "ZYGDSYLZQJZB": null,
        "YYFXZB": null,
        "JJYWFXZB": null,
        "ZQZYYWFXZB": null,
        "ZQCXYWFXZB": null,
        "RZRQYWFXZB": null,
        "EPSJBTZ": 25.352112676056,
        "BPSTZ": 17.532124539,
        "MGZBGJTZ": 3.686585879962,
        "MGWFPLRTZ": 27.346251786625,
        "MGJYXJJETZ": -13.796411040509,
        "ROEJQTZ": 7.8309509012,
        "ZZCJLLTZ": -12.306413023081,
        "ZCFZLTZ": 69.099063270534,
        "REPORT_YEAR": "2024",
        "ROIC": 13.260147942113,
        "ROICTZ": -7.96514451713,
        "NBV_LIFE": null,
        "NBV_RATE": null,
        "NHJZ_CURRENT_AMT": null,
        "TOTAL_ASSETS_PK": 3877422385.61,
        "OPERATE_INCOME_PK": 1475741034.67,
        "OPERATE_PROFIT_PK": 410499944.56,
        "NETCASH_OPERATE_PK": 332405825.62,
        "NETCASH_INVEST_PK": -726773650.43,
        "NETCASH_FINANCE_PK": 734367124.81,
        "SALE_ER_PK": 29.1822344316,
        "RE_RATIO_PK": 9.916393305599,
        "OI_YOYRATIO_PK": 16.8875197863,
        "TA_YOYRATIO_PK": 50.6022864198,
        "EQUITY_YOYRATIO_PK": 18.4969643874,
        "TOTAL_EQUITY_PK": 2331528721.53,
        "TOTAL_SHARE": 406183234,
        "A_FREE_SHARE": 406183234,
        "B_FREE_SHARE": null,
        "DJD_TOI_YOY": 13.945857715743,
        "DJD_DPNP_YOY": 24.83502509635,
        "DJD_DEDUCTDPNP_YOY": 4.258659704562,
        "DJD_TOI_QOQ": 8.318730435115,
        "DJD_DPNP_QOQ": -25.42555131165,
        "DJD_DEDUCTDPNP_QOQ": -26.534386602559,
        "XSMLL_TB": 4.727433987238,
        "PER_TOI": 3.633085179951,
        "PER_OI": 3.633085179951,
        "PER_EBIT": 1.005002330383,
        "STAFF_NUM": 1784,
        "AVG_TOI": 827209.100151345,
        "AVG_NET_PROFIT": 198874.457982063,
        "PREPAID_ACCOUNTS_RATIO": 185.857790155463,
        "ACCOUNTS_PAYABLE_TR": 2.63665241006,
        "FIXED_ASSET_TR": 2.482804055727,
        "CURRENT_ASSET_TR": 0.864817725016,
        "PREPAID_ACCOUNTS_TDAYS": 1.936964814329,
        "INVENTORY_TR_YOY": -4.590311833482,
        "PAYABLE_TDAYS": 136.536768603415,
        "OPERATE_CYCLE": 401.317965635002,
        "GUARD_SPEED_RATIO": 2.675115800046,
        "CASH_RATIO": 2.009765865347,
        "INTEREST_COVERAGE_RATIO": 21.068009164035,
        "CA_TA": 52.7875428632,
        "NCA_TA": 47.2124571368,
        "LIQUIDATION_RATIO": 239.35534858551,
        "INTEREST_DEBT_RATIO": 24.4454099372,
        "FC_LIABILITIES": 144.621478361313,
        "FCFF_FORWARD": -517998858.530719,
        "FCFF_BACK": -744292416.282909,
        "SS_OI": 0.946307295726,
        "SS_TA": 0.360163110651,
        "NCO_OP": 0.809758515257,
        "NCO_NETPROFIT": 0.936903297326,
        "NCO_FIXED": 0.547794223508,
        "FIRST_ADEQUACY_RATIO": null,
        "NET_INTEREST_SPREAD": null,
        "NET_INTEREST_MARGIN": null,
        "LOAN_ADVANCES": null,
        "NON_PERFORMING_LOAN": null,
        "OVERDUE_LOANS": null,
        "LOAN_PROVISION_RATIO": null,
        "REVENUE_RATIO": null,
        "LIABILITY": 1545893664.08,
        "CAPITAL_PROVISIONS_SUM": null,
        "RISK_COVERAGE": null,
        "CAPITAL_LEVERAGE_RATIO": null,
        "LIQUIDITY_COVERAGE_RATIO": null,
        "NET_FUNDING_RATIO": null,
        "NET_CAPITAL_LIABILITIES": null,
        "NET_ASSETS_LIABILITIES": null,
        "PROPRIETARY_CAPITAL": null,
        "IS_BZ": "0",
        "RDPERSONNEL": 269,
        "PRATIO": 15.08,
        "RDEXPEND": 146340285.17,
        "RCAPITAL_RATIO": 0,
        "RCOST_RATIO": 100,
        "TOTALOPER_RATIO": 1008.43115957829,
        "INTSTCOVRATE": 26.820650663424,
        "CL_TL": 34.4161471848
      },
      {
        "SECUCODE": "605116.SH",
        "SECURITY_CODE": "605116",
        "SECURITY_NAME_ABBR": "奥锐特",
        "ORG_CODE": "10000015507",
        "ORG_TYPE": "通用",
        "REPORT_DATE": "2024-09-30 00:00:00",
        "REPORT_TYPE": "三季报",
        "REPORT_DATE_NAME": "2024三季报",
        "SECURITY_TYPE_CODE": "058001001",
        "NOTICE_DATE": "2024-10-25 00:00:00",
        "UPDATE_DATE": "2025-10-31 00:00:00",
        "CURRENCY": "CNY",
        "EPSJB": 0.7,
        "EPSKCJB": null,
        "EPSXS": 0.68,
        "BPS": 5.368686775243,
        "MGZBGJ": 1.47959849102,
        "MGWFPLR": 2.649297402479,
        "MGJYXJJE": 0.742219339357,
        "TOTALOPERATEREVE": 1088322409.18,
        "MLR": 633652761.56,
        "PARENTNETPROFIT": 283794989.04,
        "KCFJCXSYJLR": 281571787.49,
        "TOTALOPERATEREVETZ": 17.971683683124,
        "PARENTNETPROFITTZ": 22.037851482939,
        "KCFJCXSYJLRTZ": 44.495652306452,
        "YYZSRGDHBZC": -0.847815643998,
        "NETPROFITRPHBZC": -10.846672352371,
        "KFJLRGDHBZC": -1.529801680801,
        "ROEJQ": 13.75,
        "ROEKCJQ": null,
        "ZZCJLL": 9.0589352662,
        "XSJLL": 26.076370995,
        "XSMLL": 58.2228902222,
        "YSZKYYSR": null,
        "XSJXLYYSR": 0.554019121121,
        "JYXJLYYSR": 0.277018815387,
        "TAXRATE": 12.5659014614,
        "LD": 3.897875012912,
        "SD": 2.816607636016,
        "XJLLB": 0.560619837384,
        "ZCFZL": 38.5461838209,
        "QYCS": 1.627238245198,
        "CQBL": 0.627238245199,
        "ZZCZZTS": 777.201730860934,
        "CHZZTS": 324.020305810285,
        "YSZKZZTS": 78.441064955892,
        "TOAZZL": 0.347400152726,
        "CHZZL": 0.833281109728,
        "YSZKZZL": 3.442074634655,
        "TOTALDEPOSITS": null,
        "GROSSLOANS": null,
        "LTDRR": null,
        "NEWCAPITALADER": null,
        "HXYJBCZL": null,
        "NONPERLOAN": null,
        "BLDKBBL": null,
        "NZBJE": null,
        "TOTAL_ROI": null,
        "NET_ROI": null,
        "EARNED_PREMIUM": null,
        "COMPENSATE_EXPENSE": null,
        "SURRENDER_RATE_LIFE": null,
        "SOLVENCY_AR": null,
        "JZB": null,
        "JZC": null,
        "JZBJZC": null,
        "ZYGPGMJZC": null,
        "ZYGDSYLZQJZB": null,
        "YYFXZB": null,
        "JJYWFXZB": null,
        "ZQZYYWFXZB": null,
        "ZQCXYWFXZB": null,
        "RZRQYWFXZB": null,
        "EPSJBTZ": 22.80701754386,
        "BPSTZ": 16.7035114959,
        "MGZBGJTZ": 4.526198900928,
        "MGWFPLRTZ": 26.959473993454,
        "MGJYXJJETZ": 4.357604576339,
        "ROEJQTZ": 4.6423135464,
        "ZZCJLLTZ": -14.330556719302,
        "ZCFZLTZ": 83.216664617558,
        "REPORT_YEAR": "2024",
        "ROIC": 10.619082553892,
        "ROICTZ": -15.153967079134,
        "NBV_LIFE": null,
        "NBV_RATE": null,
        "NHJZ_CURRENT_AMT": null,
        "TOTAL_ASSETS_PK": 3690915800.95,
        "OPERATE_INCOME_PK": 1088322409.18,
        "OPERATE_PROFIT_PK": 326077392.08,
        "NETCASH_OPERATE_PK": 301485784.55,
        "NETCASH_INVEST_PK": -592857828.73,
        "NETCASH_FINANCE_PK": 736301362,
        "SALE_ER_PK": 27.890771774,
        "RE_RATIO_PK": 9.681923606571,
        "OI_YOYRATIO_PK": 17.9716836831,
        "TA_YOYRATIO_PK": 55.9661579224,
        "EQUITY_YOYRATIO_PK": 21.384792095,
        "TOTAL_EQUITY_PK": 2268208611.64,
        "TOTAL_SHARE": 406183234,
        "A_FREE_SHARE": 406183234,
        "B_FREE_SHARE": null,
        "DJD_TOI_YOY": -3.301923543059,
        "DJD_DPNP_YOY": -30.330636776019,
        "DJD_DEDUCTDPNP_YOY": -6.243553396964,
        "DJD_TOI_QOQ": -9.459555078498,
        "DJD_DPNP_QOQ": -10.530232517545,
        "DJD_DEDUCTDPNP_QOQ": -9.992611770714,
        "XSMLL_TB": 4.644176702936,
        "PER_TOI": 2.679310206133,
        "PER_OI": 2.679310206133,
        "PER_EBIT": 0.782589834858,
        "STAFF_NUM": null,
        "AVG_TOI": null,
        "AVG_NET_PROFIT": null,
        "PREPAID_ACCOUNTS_RATIO": 85.761290704446,
        "ACCOUNTS_PAYABLE_TR": 2.424004152895,
        "FIXED_ASSET_TR": 1.869156651052,
        "CURRENT_ASSET_TR": 0.628686515054,
        "PREPAID_ACCOUNTS_TDAYS": 3.148273513402,
        "INVENTORY_TR_YOY": -4.358878201859,
        "PAYABLE_TDAYS": 111.385947782943,
        "OPERATE_CYCLE": 402.453447430481,
        "GUARD_SPEED_RATIO": 2.772505699323,
        "CASH_RATIO": 2.097012459002,
        "INTEREST_COVERAGE_RATIO": null,
        "CA_TA": 56.7926520602,
        "NCA_TA": 43.2073479398,
        "LIQUIDATION_RATIO": 250.047994283724,
        "INTEREST_DEBT_RATIO": 23.4679520662,
        "FC_LIABILITIES": 163.090369565658,
        "FCFF_FORWARD": -518558927.750247,
        "FCFF_BACK": -853660739.20919,
        "SS_OI": 1.042000774462,
        "SS_TA": 0.307249705598,
        "NCO_OP": 0.924583524871,
        "NCO_NETPROFIT": 1.062336532332,
        "NCO_FIXED": 0.517532568526,
        "FIRST_ADEQUACY_RATIO": null,
        "NET_INTEREST_SPREAD": null,
        "NET_INTEREST_MARGIN": null,
        "LOAN_ADVANCES": null,
        "NON_PERFORMING_LOAN": null,
        "OVERDUE_LOANS": null,
        "LOAN_PROVISION_RATIO": null,
        "REVENUE_RATIO": null,
        "LIABILITY": 1422707189.31,
        "CAPITAL_PROVISIONS_SUM": null,
        "RISK_COVERAGE": null,
        "CAPITAL_LEVERAGE_RATIO": null,
        "LIQUIDITY_COVERAGE_RATIO": null,
        "NET_FUNDING_RATIO": null,
        "NET_CAPITAL_LIABILITIES": null,
        "NET_ASSETS_LIABILITIES": null,
        "PROPRIETARY_CAPITAL": null,
        "IS_BZ": "0",
        "RDPERSONNEL": null,
        "PRATIO": null,
        "RDEXPEND": null,
        "RCAPITAL_RATIO": null,
        "RCOST_RATIO": null,
        "TOTALOPER_RATIO": null,
        "INTSTCOVRATE": 53.514143642366,
        "CL_TL": 37.7992212256
      },
      {
        "SECUCODE": "605116.SH",
        "SECURITY_CODE": "605116",
        "SECURITY_NAME_ABBR": "奥锐特",
        "ORG_CODE": "10000015507",
        "ORG_TYPE": "通用",
        "REPORT_DATE": "2024-06-30 00:00:00",
        "REPORT_TYPE": "中报",
        "REPORT_DATE_NAME": "2024中报",
        "SECURITY_TYPE_CODE": "058001001",
        "NOTICE_DATE": "2024-08-29 00:00:00",
        "UPDATE_DATE": "2025-08-29 00:00:00",
        "CURRENCY": "CNY",
        "EPSJB": 0.46,
        "EPSKCJB": 0.46,
        "EPSXS": 0.46,
        "BPS": 5.120320101454,
        "MGZBGJ": 1.466409397728,
        "MGWFPLR": 2.414920050961,
        "MGJYXJJE": 0.41192377789,
        "TOTALOPERATEREVE": 730657004.56,
        "MLR": 416616505.02,
        "PARENTNETPROFIT": 188592080.74,
        "KCFJCXSYJLR": 187113195.53,
        "TOTALOPERATEREVETZ": 32.209719022036,
        "PARENTNETPROFITTZ": 96.660898585196,
        "KCFJCXSYJLRTZ": 96.965043084102,
        "YYZSRGDHBZC": 11.151061839157,
        "NETPROFITRPHBZC": 17.31170217545,
        "KFJLRGDHBZC": 17.943088925151,
        "ROEJQ": 9.26,
        "ROEKCJQ": 9.19,
        "ZZCJLL": 6.9283039069,
        "XSJLL": 25.8113012758,
        "XSMLL": 57.0194362635,
        "YSZKYYSR": null,
        "XSJXLYYSR": 0.52212975511,
        "JYXJLYYSR": 0.229001265869,
        "TAXRATE": 12.8387889282,
        "LD": 2.222329612424,
        "SD": 1.332841791016,
        "XJLLB": 0.268606113809,
        "ZCFZL": 27.5186537609,
        "QYCS": 1.379665323408,
        "CQBL": 0.379665323408,
        "ZZCZZTS": 670.58753369717,
        "CHZZTS": 304.895546834557,
        "YSZKZZTS": 78.171929243729,
        "TOAZZL": 0.268421333465,
        "CHZZL": 0.590366116753,
        "YSZKZZL": 2.302616831149,
        "TOTALDEPOSITS": null,
        "GROSSLOANS": null,
        "LTDRR": null,
        "NEWCAPITALADER": null,
        "HXYJBCZL": null,
        "NONPERLOAN": null,
        "BLDKBBL": null,
        "NZBJE": null,
        "TOTAL_ROI": null,
        "NET_ROI": null,
        "EARNED_PREMIUM": null,
        "COMPENSATE_EXPENSE": null,
        "SURRENDER_RATE_LIFE": null,
        "SOLVENCY_AR": null,
        "JZB": null,
        "JZC": null,
        "JZBJZC": null,
        "ZYGPGMJZC": null,
        "ZYGDSYLZQJZB": null,
        "YYFXZB": null,
        "JJYWFXZB": null,
        "ZQZYYWFXZB": null,
        "ZQCXYWFXZB": null,
        "RZRQYWFXZB": null,
        "EPSJBTZ": 91.666666666667,
        "BPSTZ": 20.375081614,
        "MGZBGJTZ": 4.145392837457,
        "MGWFPLRTZ": 37.970752263822,
        "MGJYXJJETZ": 13.382375585225,
        "ROEJQTZ": 66.2477558348,
        "ZZCJLLTZ": 49.55757356772,
        "ZCFZLTZ": 44.838239345498,
        "REPORT_YEAR": "2024",
        "ROIC": 8.224115738991,
        "ROICTZ": 51.550231159926,
        "NBV_LIFE": null,
        "NBV_RATE": null,
        "NHJZ_CURRENT_AMT": null,
        "TOTAL_ASSETS_PK": 2869494748,
        "OPERATE_INCOME_PK": 730657004.56,
        "OPERATE_PROFIT_PK": 217574853.47,
        "NETCASH_OPERATE_PK": 167321378.96,
        "NETCASH_INVEST_PK": -132975765.43,
        "NETCASH_FINANCE_PK": -8851301.04,
        "SALE_ER_PK": 26.7376215325,
        "RE_RATIO_PK": 8.956336099099,
        "OI_YOYRATIO_PK": 32.209719022,
        "TA_YOYRATIO_PK": 33.7155265727,
        "EQUITY_YOYRATIO_PK": 19.652232651,
        "TOTAL_EQUITY_PK": 2079848423.61,
        "TOTAL_SHARE": 406183234,
        "A_FREE_SHARE": 406183234,
        "B_FREE_SHARE": null,
        "DJD_TOI_YOY": 57.689287527973,
        "DJD_DPNP_YOY": 112.733944344367,
        "DJD_DEDUCTDPNP_YOY": 108.729263676934,
        "DJD_TOI_QOQ": 17.701607533364,
        "DJD_DPNP_QOQ": 29.474940920942,
        "DJD_DEDUCTDPNP_QOQ": 27.720774977877,
        "XSMLL_TB": 14.512785009468,
        "PER_TOI": 1.798783846576,
        "PER_OI": 1.798783846576,
        "PER_EBIT": 0.510861487635,
        "STAFF_NUM": null,
        "AVG_TOI": null,
        "AVG_NET_PROFIT": null,
        "PREPAID_ACCOUNTS_RATIO": 77.033394613959,
        "ACCOUNTS_PAYABLE_TR": 1.499358185278,
        "FIXED_ASSET_TR": 1.244401050253,
        "CURRENT_ASSET_TR": 0.531312503165,
        "PREPAID_ACCOUNTS_TDAYS": 2.336648941697,
        "INVENTORY_TR_YOY": 0.362466348282,
        "PAYABLE_TDAYS": 120.051367156558,
        "OPERATE_CYCLE": 383.050549431926,
        "GUARD_SPEED_RATIO": 1.290363187202,
        "CASH_RATIO": 0.717446230587,
        "INTEREST_COVERAGE_RATIO": 165.220323326556,
        "CA_TA": 48.2434747718,
        "NCA_TA": 51.7565252282,
        "LIQUIDATION_RATIO": 346.209549375396,
        "INTEREST_DEBT_RATIO": 7.1958709377,
        "FC_LIABILITIES": 71.744623058693,
        "FCFF_FORWARD": -62983843.7472462,
        "FCFF_BACK": 75122898.6526594,
        "SS_OI": 0.923603577846,
        "SS_TA": 0.235176392659,
        "NCO_OP": 0.769029032039,
        "NCO_NETPROFIT": 0.887213176203,
        "NCO_FIXED": 0.282470781367,
        "FIRST_ADEQUACY_RATIO": null,
        "NET_INTEREST_SPREAD": null,
        "NET_INTEREST_MARGIN": null,
        "LOAN_ADVANCES": null,
        "NON_PERFORMING_LOAN": null,
        "OVERDUE_LOANS": null,
        "LOAN_PROVISION_RATIO": null,
        "REVENUE_RATIO": null,
        "LIABILITY": 789646324.39,
        "CAPITAL_PROVISIONS_SUM": null,
        "RISK_COVERAGE": null,
        "CAPITAL_LEVERAGE_RATIO": null,
        "LIQUIDITY_COVERAGE_RATIO": null,
        "NET_FUNDING_RATIO": null,
        "NET_CAPITAL_LIABILITIES": null,
        "NET_ASSETS_LIABILITIES": null,
        "PROPRIETARY_CAPITAL": null,
        "IS_BZ": "0",
        "RDPERSONNEL": null,
        "PRATIO": null,
        "RDEXPEND": 65440097.06,
        "RCAPITAL_RATIO": null,
        "RCOST_RATIO": 100,
        "TOTALOPER_RATIO": 1116.52799642104,
        "INTSTCOVRATE": 214.654590702954,
        "CL_TL": 78.8865427761
      },
      {
        "SECUCODE": "605116.SH",
        "SECURITY_CODE": "605116",
        "SECURITY_NAME_ABBR": "奥锐特",
        "ORG_CODE": "10000015507",
        "ORG_TYPE": "通用",
        "REPORT_DATE": "2024-03-31 00:00:00",
        "REPORT_TYPE": "一季报",
        "REPORT_DATE_NAME": "2024一季报",
        "SECURITY_TYPE_CODE": "058001001",
        "NOTICE_DATE": "2024-04-29 00:00:00",
        "UPDATE_DATE": "2025-04-26 00:00:00",
        "CURRENCY": "CNY",
        "EPSJB": 0.2,
        "EPSKCJB": null,
        "EPSXS": 0.2,
        "BPS": 5.065116917367,
        "MGZBGJ": 1.453220304435,
        "MGWFPLR": 2.372957425916,
        "MGJYXJJE": 0.22015758355,
        "TOTALOPERATEREVE": 335623155.4,
        "MLR": 180165181.85,
        "PARENTNETPROFIT": 82184172.26,
        "KCFJCXSYJLR": 82167819.58,
        "TOTALOPERATEREVETZ": 11.083497980175,
        "PARENTNETPROFITTZ": 79.136938405963,
        "KCFJCXSYJLRTZ": 87.434720693306,
        "YYZSRGDHBZC": 2.652388923211,
        "NETPROFITRPHBZC": 12.544537642716,
        "KFJLRGDHBZC": 14.661827744403,
        "ROEJQ": 3.14,
        "ROEKCJQ": null,
        "ZZCJLL": 3.1238174431,
        "XSJLL": 24.4870387927,
        "XSMLL": 53.6807961403,
        "YSZKYYSR": null,
        "XSJXLYYSR": 0.583110368076,
        "JYXJLYYSR": 0.266450357227,
        "TAXRATE": 17.076267573,
        "LD": 2.767577807693,
        "SD": 1.716501862035,
        "XJLLB": 0.182893826472,
        "ZCFZL": 23.4351753498,
        "QYCS": 1.306082792678,
        "CQBL": 0.306082792677,
        "ZZCZZTS": 705.49368889843,
        "CHZZTS": 296.336111596746,
        "YSZKZZTS": 76.378635103278,
        "TOAZZL": 0.127570241118,
        "CHZZL": 0.30370918858,
        "YSZKZZL": 1.178339988379,
        "TOTALDEPOSITS": null,
        "GROSSLOANS": null,
        "LTDRR": null,
        "NEWCAPITALADER": null,
        "HXYJBCZL": null,
        "NONPERLOAN": null,
        "BLDKBBL": null,
        "NZBJE": null,
        "TOTAL_ROI": null,
        "NET_ROI": null,
        "EARNED_PREMIUM": null,
        "COMPENSATE_EXPENSE": null,
        "SURRENDER_RATE_LIFE": null,
        "SOLVENCY_AR": null,
        "JZB": null,
        "JZC": null,
        "JZBJZC": null,
        "ZYGPGMJZC": null,
        "ZYGDSYLZQJZB": null,
        "YYFXZB": null,
        "JJYWFXZB": null,
        "ZQZYYWFXZB": null,
        "ZQCXYWFXZB": null,
        "RZRQYWFXZB": null,
        "EPSJBTZ": 81.818181818182,
        "BPSTZ": 18.7152680918,
        "MGZBGJTZ": 4.912979796228,
        "MGWFPLRTZ": 32.777222263558,
        "MGJYXJJETZ": 11.980867130446,
        "ROEJQTZ": 16.2962962963,
        "ZZCJLLTZ": 41.626585531556,
        "ZCFZLTZ": 34.159692557322,
        "REPORT_YEAR": "2024",
        "ROIC": 3.493048445239,
        "ROICTZ": 36.927067051525,
        "NBV_LIFE": null,
        "NBV_RATE": null,
        "NHJZ_CURRENT_AMT": null,
        "TOTAL_ASSETS_PK": 2687167606.86,
        "OPERATE_INCOME_PK": 335623155.4,
        "OPERATE_PROFIT_PK": 100448940.91,
        "NETCASH_OPERATE_PK": 89426909.65,
        "NETCASH_INVEST_PK": -140019195.38,
        "NETCASH_FINANCE_PK": 32322871.92,
        "SALE_ER_PK": 23.4672307833,
        "RE_RATIO_PK": 8.620407592414,
        "OI_YOYRATIO_PK": 11.0834979802,
        "TA_YOYRATIO_PK": 27.3814174336,
        "EQUITY_YOYRATIO_PK": 18.1717395086,
        "TOTAL_EQUITY_PK": 2057425166.25,
        "TOTAL_SHARE": 406183234,
        "A_FREE_SHARE": 406183234,
        "B_FREE_SHARE": null,
        "DJD_TOI_YOY": 11.083497980175,
        "DJD_DPNP_YOY": 79.136938405963,
        "DJD_DEDUCTDPNP_YOY": 87.434720693306,
        "DJD_TOI_QOQ": -1.287997542844,
        "DJD_DPNP_QOQ": 44.505498096511,
        "DJD_DEDUCTDPNP_QOQ": 23.449212426888,
        "XSMLL_TB": 17.824236276794,
        "PER_TOI": 0.826261168651,
        "PER_OI": 0.826261168651,
        "PER_EBIT": 0.226190844717,
        "STAFF_NUM": null,
        "AVG_TOI": null,
        "AVG_NET_PROFIT": null,
        "PREPAID_ACCOUNTS_RATIO": 38.042935416233,
        "ACCOUNTS_PAYABLE_TR": 0.940306398325,
        "FIXED_ASSET_TR": 0.580478081776,
        "CURRENT_ASSET_TR": 0.246848612209,
        "PREPAID_ACCOUNTS_TDAYS": 2.365748042713,
        "INVENTORY_TR_YOY": -18.225384280218,
        "PAYABLE_TDAYS": 95.713482499237,
        "OPERATE_CYCLE": 372.726304570709,
        "GUARD_SPEED_RATIO": 1.67912846475,
        "CASH_RATIO": 1.091244993018,
        "INTEREST_COVERAGE_RATIO": null,
        "CA_TA": 50.3586710474,
        "NCA_TA": 49.6413289526,
        "LIQUIDATION_RATIO": 405.109747025916,
        "INTEREST_DEBT_RATIO": 5.5707143443,
        "FC_LIABILITIES": 109.124499301824,
        "FCFF_FORWARD": -78697399.508246,
        "FCFF_BACK": -63620258.6470538,
        "SS_OI": 1.003895221259,
        "SS_TA": 0.125384989381,
        "NCO_OP": 0.890272299935,
        "NCO_NETPROFIT": 1.088128129673,
        "NCO_FIXED": 0.155685821638,
        "FIRST_ADEQUACY_RATIO": null,
        "NET_INTEREST_SPREAD": null,
        "NET_INTEREST_MARGIN": null,
        "LOAN_ADVANCES": null,
        "NON_PERFORMING_LOAN": null,
        "OVERDUE_LOANS": null,
        "LOAN_PROVISION_RATIO": null,
        "REVENUE_RATIO": null,
        "LIABILITY": 629742440.61,
        "CAPITAL_PROVISIONS_SUM": null,
        "RISK_COVERAGE": null,
        "CAPITAL_LEVERAGE_RATIO": null,
        "LIQUIDITY_COVERAGE_RATIO": null,
        "NET_FUNDING_RATIO": null,
        "NET_CAPITAL_LIABILITIES": null,
        "NET_ASSETS_LIABILITIES": null,
        "PROPRIETARY_CAPITAL": null,
        "IS_BZ": "0",
        "RDPERSONNEL": null,
        "PRATIO": null,
        "RDEXPEND": null,
        "RCAPITAL_RATIO": null,
        "RCOST_RATIO": null,
        "TOTALOPER_RATIO": null,
        "INTSTCOVRATE": 168.892951001631,
        "CL_TL": 77.6436983708
      },
      {
        "SECUCODE": "605116.SH",
        "SECURITY_CODE": "605116",
        "SECURITY_NAME_ABBR": "奥锐特",
        "ORG_CODE": "10000015507",
        "ORG_TYPE": "通用",
        "REPORT_DATE": "2023-12-31 00:00:00",
        "REPORT_TYPE": "年报",
        "REPORT_DATE_NAME": "2023年报",
        "SECURITY_TYPE_CODE": "058001001",
        "NOTICE_DATE": "2024-04-29 00:00:00",
        "UPDATE_DATE": "2025-04-26 00:00:00",
        "CURRENCY": "CNY",
        "EPSJB": 0.71,
        "EPSKCJB": 0.64,
        "EPSXS": 0.71,
        "BPS": 4.843942416081,
        "MGZBGJ": 1.440031211142,
        "MGWFPLR": 2.17063053302,
        "MGJYXJJE": 0.949311421017,
        "TOTALOPERATEREVE": 1262530882.14,
        "MLR": 705973066.83,
        "PARENTNETPROFIT": 289419389.73,
        "KCFJCXSYJLR": 261425250.85,
        "TOTALOPERATEREVETZ": 25.241577927518,
        "PARENTNETPROFITTZ": 37.188582534308,
        "KCFJCXSYJLRTZ": 26.376252792376,
        "YYZSRGDHBZC": 8.684558035907,
        "NETPROFITRPHBZC": 12.593800457261,
        "KFJLRGDHBZC": 19.378624851064,
        "ROEJQ": 16.09,
        "ROEKCJQ": 14.54,
        "ZZCJLL": 12.5412100862,
        "XSJLL": 22.8960354395,
        "XSMLL": 55.9172909603,
        "YSZKYYSR": null,
        "XSJXLYYSR": 0.564133371425,
        "JYXJLYYSR": 0.305422669746,
        "TAXRATE": 12.1582374749,
        "LD": 2.726497785035,
        "SD": 1.708981973009,
        "XJLLB": 0.76963470665,
        "ZCFZL": 23.5773669141,
        "QYCS": 1.308512883711,
        "CQBL": 0.30851288371,
        "ZZCZZTS": 657.239030488952,
        "CHZZTS": 308.778298590984,
        "YSZKZZTS": 72.412185030628,
        "TOAZZL": 0.547745923933,
        "CHZZL": 1.165885043226,
        "YSZKZZL": 4.971538973002,
        "TOTALDEPOSITS": null,
        "GROSSLOANS": null,
        "LTDRR": null,
        "NEWCAPITALADER": null,
        "HXYJBCZL": null,
        "NONPERLOAN": null,
        "BLDKBBL": null,
        "NZBJE": null,
        "TOTAL_ROI": null,
        "NET_ROI": null,
        "EARNED_PREMIUM": null,
        "COMPENSATE_EXPENSE": null,
        "SURRENDER_RATE_LIFE": null,
        "SOLVENCY_AR": null,
        "JZB": null,
        "JZC": null,
        "JZBJZC": null,
        "ZYGPGMJZC": null,
        "ZYGDSYLZQJZB": null,
        "YYFXZB": null,
        "JJYWFXZB": null,
        "ZQZYYWFXZB": null,
        "ZQCXYWFXZB": null,
        "RZRQYWFXZB": null,
        "EPSJBTZ": 36.538461538462,
        "BPSTZ": 17.3849669639,
        "MGZBGJTZ": 5.706342728675,
        "MGWFPLRTZ": 29.646471691302,
        "MGJYXJJETZ": 131.722359346264,
        "ROEJQTZ": 20.1643017177,
        "ZZCJLLTZ": 13.103074974639,
        "ZCFZLTZ": 36.663832419477,
        "REPORT_YEAR": "2023",
        "ROIC": 14.407745709538,
        "ROICTZ": 14.725415254956,
        "NBV_LIFE": null,
        "NBV_RATE": null,
        "NHJZ_CURRENT_AMT": null,
        "TOTAL_ASSETS_PK": 2574610570.52,
        "OPERATE_INCOME_PK": 1262530882.14,
        "OPERATE_PROFIT_PK": 330727138.58,
        "NETCASH_OPERATE_PK": 385605552.66,
        "NETCASH_INVEST_PK": -365272711.43,
        "NETCASH_FINANCE_PK": 49019558.18,
        "SALE_ER_PK": 30.9621556375,
        "RE_RATIO_PK": 10.842216221117,
        "OI_YOYRATIO_PK": 25.2415779275,
        "TA_YOYRATIO_PK": 26.4976101935,
        "EQUITY_YOYRATIO_PK": 16.8280916266,
        "TOTAL_EQUITY_PK": 1967585189.7,
        "TOTAL_SHARE": 406183234,
        "A_FREE_SHARE": 406183234,
        "B_FREE_SHARE": null,
        "DJD_TOI_YOY": 42.1899257944,
        "DJD_DPNP_YOY": 131.47010016858,
        "DJD_DEDUCTDPNP_YOY": 175.918259681964,
        "DJD_TOI_QOQ": -8.077282603259,
        "DJD_DPNP_QOQ": -58.380635972262,
        "DJD_DEDUCTDPNP_QOQ": -33.934745764288,
        "XSMLL_TB": 8.318421373117,
        "PER_TOI": 3.108189126257,
        "PER_OI": 3.108189126257,
        "PER_EBIT": 0.776212739472,
        "STAFF_NUM": 1521,
        "AVG_TOI": 830066.326193294,
        "AVG_NET_PROFIT": 190282.307514793,
        "PREPAID_ACCOUNTS_RATIO": 79.373959610861,
        "ACCOUNTS_PAYABLE_TR": 3.854772342297,
        "FIXED_ASSET_TR": 2.177540905994,
        "CURRENT_ASSET_TR": 1.028790319741,
        "PREPAID_ACCOUNTS_TDAYS": 4.535492518767,
        "INVENTORY_TR_YOY": -7.750747107224,
        "PAYABLE_TDAYS": 93.390729213721,
        "OPERATE_CYCLE": 381.187090112069,
        "GUARD_SPEED_RATIO": 1.679270726812,
        "CASH_RATIO": 1.089443470924,
        "INTEREST_COVERAGE_RATIO": 140.512438225339,
        "CA_TA": 53.0581662622,
        "NCA_TA": 46.9418337378,
        "LIQUIDATION_RATIO": 401.782222225269,
        "INTEREST_DEBT_RATIO": 4.5398278753,
        "FC_LIABILITIES": 108.944347092362,
        "FCFF_FORWARD": 67078224.5476964,
        "FCFF_BACK": -45698806.9379404,
        "SS_OI": 0.932797396927,
        "SS_TA": 0.457422778375,
        "NCO_OP": 1.165932600257,
        "NCO_NETPROFIT": 1.333954389407,
        "NCO_FIXED": 0.662595984328,
        "FIRST_ADEQUACY_RATIO": null,
        "NET_INTEREST_SPREAD": null,
        "NET_INTEREST_MARGIN": null,
        "LOAN_ADVANCES": null,
        "NON_PERFORMING_LOAN": null,
        "OVERDUE_LOANS": null,
        "LOAN_PROVISION_RATIO": null,
        "REVENUE_RATIO": null,
        "LIABILITY": 607025380.82,
        "CAPITAL_PROVISIONS_SUM": null,
        "RISK_COVERAGE": null,
        "CAPITAL_LEVERAGE_RATIO": null,
        "LIQUIDITY_COVERAGE_RATIO": null,
        "NET_FUNDING_RATIO": null,
        "NET_CAPITAL_LIABILITIES": null,
        "NET_ASSETS_LIABILITIES": null,
        "PROPRIETARY_CAPITAL": null,
        "IS_BZ": "0",
        "RDPERSONNEL": 248,
        "PRATIO": 16.31,
        "RDEXPEND": 136886328.1,
        "RCAPITAL_RATIO": 0,
        "RCOST_RATIO": 100,
        "TOTALOPER_RATIO": 922.320658070161,
        "INTSTCOVRATE": 120.9147891752,
        "CL_TL": 82.5375902196
      },
      {
        "SECUCODE": "605116.SH",
        "SECURITY_CODE": "605116",
        "SECURITY_NAME_ABBR": "奥锐特",
        "ORG_CODE": "10000015507",
        "ORG_TYPE": "通用",
        "REPORT_DATE": "2023-09-30 00:00:00",
        "REPORT_TYPE": "三季报",
        "REPORT_DATE_NAME": "2023三季报",
        "SECURITY_TYPE_CODE": "058001001",
        "NOTICE_DATE": "2023-10-31 00:00:00",
        "UPDATE_DATE": "2024-10-25 00:00:00",
        "CURRENCY": "CNY",
        "EPSJB": 0.57,
        "EPSKCJB": null,
        "EPSXS": 0.57,
        "BPS": 4.600278694642,
        "MGZBGJ": 1.415528840212,
        "MGWFPLR": 2.086726826401,
        "MGJYXJJE": 0.711226884107,
        "TOTALOPERATEREVE": 922528504.47,
        "MLR": 513284900.65,
        "PARENTNETPROFIT": 232546693.99,
        "KCFJCXSYJLR": 194865231.58,
        "TOTALOPERATEREVETZ": 19.971247124873,
        "PARENTNETPROFITTZ": 24.760544570515,
        "KCFJCXSYJLRTZ": 6.676101692469,
        "YYZSRGDHBZC": 10.444782689386,
        "NETPROFITRPHBZC": 35.249914180943,
        "KFJLRGDHBZC": 16.51210397613,
        "ROEJQ": 13.14,
        "ROEKCJQ": null,
        "ZZCJLL": 10.5742898743,
        "XSJLL": 25.2272911723,
        "XSMLL": 55.6389204413,
        "YSZKYYSR": null,
        "XSJXLYYSR": 0.585885992423,
        "JYXJLYYSR": 0.31315759111,
        "TAXRATE": 12.1116897038,
        "LD": 3.078252008379,
        "SD": 1.909169528959,
        "XJLLB": 0.683011754229,
        "ZCFZL": 21.0385795972,
        "QYCS": 1.266441250548,
        "CQBL": 0.266441250548,
        "ZZCZZTS": 644.144306378314,
        "CHZZTS": 309.896655330723,
        "YSZKZZTS": 70.392733709411,
        "TOAZZL": 0.419160733591,
        "CHZZL": 0.871258193193,
        "YSZKZZL": 3.835623164098,
        "TOTALDEPOSITS": null,
        "GROSSLOANS": null,
        "LTDRR": null,
        "NEWCAPITALADER": null,
        "HXYJBCZL": null,
        "NONPERLOAN": null,
        "BLDKBBL": null,
        "NZBJE": null,
        "TOTAL_ROI": null,
        "NET_ROI": null,
        "EARNED_PREMIUM": null,
        "COMPENSATE_EXPENSE": null,
        "SURRENDER_RATE_LIFE": null,
        "SOLVENCY_AR": null,
        "JZB": null,
        "JZC": null,
        "JZBJZC": null,
        "ZYGPGMJZC": null,
        "ZYGDSYLZQJZB": null,
        "YYFXZB": null,
        "JJYWFXZB": null,
        "ZQZYYWFXZB": null,
        "ZQCXYWFXZB": null,
        "RZRQYWFXZB": null,
        "EPSJBTZ": 23.913043478261,
        "BPSTZ": 12.2818068107,
        "MGZBGJTZ": 15.434530537488,
        "MGWFPLRTZ": 24.493724668685,
        "MGJYXJJETZ": 221.9192904485,
        "ROEJQTZ": 11.544991511,
        "ZZCJLLTZ": 1.901504797573,
        "ZCFZLTZ": 85.833118151981,
        "REPORT_YEAR": "2023",
        "ROIC": 12.515708971091,
        "ROICTZ": 9.709279720594,
        "NBV_LIFE": null,
        "NBV_RATE": null,
        "NHJZ_CURRENT_AMT": null,
        "TOTAL_ASSETS_PK": 2366485044.01,
        "OPERATE_INCOME_PK": 922528504.47,
        "OPERATE_PROFIT_PK": 265332023,
        "NETCASH_OPERATE_PK": 288896804.19,
        "NETCASH_INVEST_PK": -133511177.24,
        "NETCASH_FINANCE_PK": 3004165.97,
        "SALE_ER_PK": 30.0231196411,
        "RE_RATIO_PK": 10.382874080951,
        "OI_YOYRATIO_PK": 19.9712471249,
        "TA_YOYRATIO_PK": 27.415808549,
        "EQUITY_YOYRATIO_PK": 13.4536744409,
        "TOTAL_EQUITY_PK": 1868610204.37,
        "TOTAL_SHARE": 406183234,
        "A_FREE_SHARE": 406183234,
        "B_FREE_SHARE": null,
        "DJD_TOI_YOY": 42.249284820774,
        "DJD_DPNP_YOY": 96.17817256362,
        "DJD_DEDUCTDPNP_YOY": 44.517748247692,
        "DJD_TOI_QOQ": 47.647799990054,
        "DJD_DPNP_QOQ": 173.194064870749,
        "DJD_DEDUCTDPNP_QOQ": 100.382763546143,
        "XSMLL_TB": 11.794337134922,
        "PER_TOI": 2.271146873964,
        "PER_OI": 2.271146873964,
        "PER_EBIT": 0.648342344834,
        "STAFF_NUM": null,
        "AVG_TOI": null,
        "AVG_NET_PROFIT": null,
        "PREPAID_ACCOUNTS_RATIO": 38.805947399999,
        "ACCOUNTS_PAYABLE_TR": 3.413988418868,
        "FIXED_ASSET_TR": 1.600139292895,
        "CURRENT_ASSET_TR": 0.771867364032,
        "PREPAID_ACCOUNTS_TDAYS": 6.957696386508,
        "INVENTORY_TR_YOY": -18.765498952945,
        "PAYABLE_TDAYS": 79.086384273537,
        "OPERATE_CYCLE": 380.274944665079,
        "GUARD_SPEED_RATIO": 1.868414482626,
        "CASH_RATIO": 1.231724277536,
        "INTEREST_COVERAGE_RATIO": null,
        "CA_TA": 55.0192881804,
        "NCA_TA": 44.9807118196,
        "LIQUIDATION_RATIO": 448.024006785096,
        "INTEREST_DEBT_RATIO": 3.819708872,
        "FC_LIABILITIES": 123.17242775364,
        "FCFF_FORWARD": 651833.439869732,
        "FCFF_BACK": -75450972.09456,
        "SS_OI": 0.950611380777,
        "SS_TA": 0.370577493257,
        "NCO_OP": 1.088812428005,
        "NCO_NETPROFIT": 1.241344498588,
        "NCO_FIXED": 0.502054835027,
        "FIRST_ADEQUACY_RATIO": null,
        "NET_INTEREST_SPREAD": null,
        "NET_INTEREST_MARGIN": null,
        "LOAN_ADVANCES": null,
        "NON_PERFORMING_LOAN": null,
        "OVERDUE_LOANS": null,
        "LOAN_PROVISION_RATIO": null,
        "REVENUE_RATIO": null,
        "LIABILITY": 497874839.64,
        "CAPITAL_PROVISIONS_SUM": null,
        "RISK_COVERAGE": null,
        "CAPITAL_LEVERAGE_RATIO": null,
        "LIQUIDITY_COVERAGE_RATIO": null,
        "NET_FUNDING_RATIO": null,
        "NET_CAPITAL_LIABILITIES": null,
        "NET_ASSETS_LIABILITIES": null,
        "PROPRIETARY_CAPITAL": null,
        "IS_BZ": "0",
        "RDPERSONNEL": null,
        "PRATIO": null,
        "RDEXPEND": null,
        "RCAPITAL_RATIO": null,
        "RCOST_RATIO": null,
        "TOTALOPER_RATIO": null,
        "INTSTCOVRATE": 163.354970112613,
        "CL_TL": 84.9560634146
      },
      {
        "SECUCODE": "605116.SH",
        "SECURITY_CODE": "605116",
        "SECURITY_NAME_ABBR": "奥锐特",
        "ORG_CODE": "10000015507",
        "ORG_TYPE": "通用",
        "REPORT_DATE": "2023-06-30 00:00:00",
        "REPORT_TYPE": "中报",
        "REPORT_DATE_NAME": "2023中报",
        "SECURITY_TYPE_CODE": "058001001",
        "NOTICE_DATE": "2023-08-30 00:00:00",
        "UPDATE_DATE": "2024-08-29 00:00:00",
        "CURRENCY": "CNY",
        "EPSJB": 0.24,
        "EPSKCJB": 0.23,
        "EPSXS": 0.24,
        "BPS": 4.253637906449,
        "MGZBGJ": 1.408040584202,
        "MGWFPLR": 1.750313027462,
        "MGJYXJJE": 0.363304945556,
        "TOTALOPERATEREVE": 552649994.24,
        "MLR": 275181422.93,
        "PARENTNETPROFIT": 95897090.93,
        "KCFJCXSYJLR": 94998174.6,
        "TOTALOPERATEREVETZ": 8.589151916016,
        "PARENTNETPROFITTZ": -17.853111530489,
        "KCFJCXSYJLRTZ": -15.898171687485,
        "YYZSRGDHBZC": -3.627476264688,
        "NETPROFITRPHBZC": -11.97971980812,
        "KFJLRGDHBZC": -11.335980674032,
        "ROEJQ": 5.57,
        "ROEKCJQ": 5.52,
        "ZZCJLL": 4.6325329715,
        "XSJLL": 17.5245520853,
        "XSMLL": 49.7930744229,
        "YSZKYYSR": null,
        "XSJXLYYSR": 0.555975457473,
        "JYXJLYYSR": 0.267027329952,
        "TAXRATE": 17.7226362825,
        "LD": 2.952603060168,
        "SD": 1.64619522901,
        "XJLLB": 0.386774120217,
        "ZCFZL": 18.9995776566,
        "QYCS": 1.234561464088,
        "CQBL": 0.234561464088,
        "ZZCZZTS": 680.927560523606,
        "CHZZTS": 306.000690589244,
        "YSZKZZTS": 71.129649869727,
        "TOAZZL": 0.264345299611,
        "CHZZL": 0.588233966575,
        "YSZKZZL": 2.530590271844,
        "TOTALDEPOSITS": null,
        "GROSSLOANS": null,
        "LTDRR": null,
        "NEWCAPITALADER": null,
        "HXYJBCZL": null,
        "NONPERLOAN": null,
        "BLDKBBL": null,
        "NZBJE": null,
        "TOTAL_ROI": null,
        "NET_ROI": null,
        "EARNED_PREMIUM": null,
        "COMPENSATE_EXPENSE": null,
        "SURRENDER_RATE_LIFE": null,
        "SOLVENCY_AR": null,
        "JZB": null,
        "JZC": null,
        "JZBJZC": null,
        "ZYGPGMJZC": null,
        "ZYGDSYLZQJZB": null,
        "YYFXZB": null,
        "JJYWFXZB": null,
        "ZQZYYWFXZB": null,
        "ZQCXYWFXZB": null,
        "RZRQYWFXZB": null,
        "EPSJBTZ": -17.241379310345,
        "BPSTZ": 8.5135392056,
        "MGZBGJTZ": 15.041042978946,
        "MGWFPLRTZ": 16.496101667805,
        "MGJYXJJETZ": 101.588479493085,
        "ROEJQTZ": -25.3351206434,
        "ZZCJLLTZ": -30.13004152771,
        "ZCFZLTZ": 63.676551085348,
        "REPORT_YEAR": "2023",
        "ROIC": 5.426659976726,
        "ROICTZ": -25.305182515313,
        "NBV_LIFE": null,
        "NBV_RATE": null,
        "NHJZ_CURRENT_AMT": null,
        "TOTAL_ASSETS_PK": 2145969747.53,
        "OPERATE_INCOME_PK": 552649994.24,
        "OPERATE_PROFIT_PK": 117962985.44,
        "NETCASH_OPERATE_PK": 147572652.36,
        "NETCASH_INVEST_PK": -107376253.23,
        "NETCASH_FINANCE_PK": -27757936.48,
        "SALE_ER_PK": 28.1226570144,
        "RE_RATIO_PK": 10.117311653444,
        "OI_YOYRATIO_PK": 8.589151916,
        "TA_YOYRATIO_PK": 20.3564574084,
        "EQUITY_YOYRATIO_PK": 10.2919282837,
        "TOTAL_EQUITY_PK": 1738244558.86,
        "TOTAL_SHARE": 406183234,
        "A_FREE_SHARE": 406183234,
        "B_FREE_SHARE": null,
        "DJD_TOI_YOY": -13.646685984562,
        "DJD_DPNP_YOY": -34.086236638885,
        "DJD_DEDUCTDPNP_YOY": -32.33867039452,
        "DJD_TOI_QOQ": -17.085640453691,
        "DJD_DPNP_QOQ": 9.027003604677,
        "DJD_DEDUCTDPNP_QOQ": 14.690711608908,
        "XSMLL_TB": -3.248137991916,
        "PER_TOI": 1.360553414592,
        "PER_OI": 1.360553414592,
        "PER_EBIT": 0.287672844865,
        "STAFF_NUM": null,
        "AVG_TOI": null,
        "AVG_NET_PROFIT": null,
        "PREPAID_ACCOUNTS_RATIO": 33.587659489002,
        "ACCOUNTS_PAYABLE_TR": 2.209611759285,
        "FIXED_ASSET_TR": 0.933764374094,
        "CURRENT_ASSET_TR": 0.499025771978,
        "PREPAID_ACCOUNTS_TDAYS": 5.359111136009,
        "INVENTORY_TR_YOY": -17.417985528874,
        "PAYABLE_TDAYS": 81.462274647853,
        "OPERATE_CYCLE": 377.147737534133,
        "GUARD_SPEED_RATIO": 1.570629969401,
        "CASH_RATIO": 0.996026582941,
        "INTEREST_COVERAGE_RATIO": 115.843770985856,
        "CA_TA": 52.4964512732,
        "NCA_TA": 47.5035487268,
        "LIQUIDATION_RATIO": 493.617745257563,
        "INTEREST_DEBT_RATIO": 2.9175541637,
        "FC_LIABILITIES": 99.602658294084,
        "FCFF_FORWARD": 22494143.8779957,
        "FCFF_BACK": 48657120.4202021,
        "SS_OI": 1.000870787144,
        "SS_TA": 0.257753509986,
        "NCO_OP": 1.251008117585,
        "NCO_NETPROFIT": 1.523732696005,
        "NCO_FIXED": 0.243490356142,
        "FIRST_ADEQUACY_RATIO": null,
        "NET_INTEREST_SPREAD": null,
        "NET_INTEREST_MARGIN": null,
        "LOAN_ADVANCES": null,
        "NON_PERFORMING_LOAN": null,
        "OVERDUE_LOANS": null,
        "LOAN_PROVISION_RATIO": null,
        "REVENUE_RATIO": null,
        "LIABILITY": 407725188.67,
        "CAPITAL_PROVISIONS_SUM": null,
        "RISK_COVERAGE": null,
        "CAPITAL_LEVERAGE_RATIO": null,
        "LIQUIDITY_COVERAGE_RATIO": null,
        "NET_FUNDING_RATIO": null,
        "NET_CAPITAL_LIABILITIES": null,
        "NET_ASSETS_LIABILITIES": null,
        "PROPRIETARY_CAPITAL": null,
        "IS_BZ": "0",
        "RDPERSONNEL": 278,
        "PRATIO": null,
        "RDEXPEND": 55913322.27,
        "RCAPITAL_RATIO": null,
        "RCOST_RATIO": null,
        "TOTALOPER_RATIO": 988.40485916989,
        "INTSTCOVRATE": 93.40245966516,
        "CL_TL": 93.5795459693
      }
    ],
    "count": 31
  },
  "success": true,
  "message": "ok",
  "code": 0
}