{
  "classifiedAnnouncements": null,
  "totalSecurities": 0,
  "totalAnnouncement": 7,
  "totalRecordNum": 7,
  "announcements": [
    {
      "id": null,
      "secCode": "002979",
      "secName": "雷赛智能",
      "orgId": "9900023947",
      "announcementId": "1225153574",
      "announcementTitle": "2026年一季度报告",
      "announcementTime": 1776873600000,
      "adjunctUrl": "finalpage/2026-04-23/1225153574.PDF",
      "adjunctSize": 178,
      "adjunctType": "PDF",
      "storageTime": null,
      "columnId": "09020202||250101||251302",
      "pageColumn": "SZZB",
      "announcementType": "01010503||010112||010305",
      "associateAnnouncement": null,
      "important": null,
      "batchNum": null,
      "announcementContent": "",
      "orgName": null,
      "tileSecName": "雷赛智能",
      "shortTitle": "2026年一季度报告",
      "announcementTypeName": null,
      "secNameList": null
    },
    {
      "id": null,
      "secCode": "002979",
      "secName": "雷赛智能",
      "orgId": "9900023947",
      "announcementId": "1225153567",
      "announcementTitle": "2025年年度报告",
      "announcementTime": 1776873600000,
      "adjunctUrl": "finalpage/2026-04-23/1225153567.PDF",
      "adjunctSize": 1275,
      "adjunctType": "PDF",
      "storageTime": null,
      "columnId": "09020202||250101||251302",
      "pageColumn": "SZZB",
      "announcementType": "01010503||010112||010301",
      "associateAnnouncement": null,
      "important": null,
      "batchNum": null,
      "announcementContent": "",
      "orgName": null,
      "tileSecName": "雷赛智能",
      "shortTitle": "2025年年度报告",
      "announcementTypeName": null,
      "secNameList": null
    },
    {
      "id": null,
      "secCode": "002979",
      "secName": "雷赛智能",
      "orgId": "9900023947",
      "announcementId": "1225153566",
      "announcementTitle": "2025年年度报告摘要",
      "announcementTime": 1776873600000,
      "adjunctUrl": "finalpage/2026-04-23/1225153566.PDF",
      "adjunctSize": 305,
      "adjunctType": "PDF",
      "storageTime": null,
      "columnId": "09020202||250101||251302",
      "pageColumn": "SZZB",
      "announcementType": "01010503||010112||010301",
      "associateAnnouncement": null,
      "important": null,
      "batchNum": null,
      "announcementContent": "",
      "orgName": null,
      "tileSecName": "雷赛智能",
      "shortTitle": "2025年年度报告摘要",
      "announcementTypeName": null,
      "secNameList": null
    },
    {
      "id": null,
      "secCode": "002979",
      "secName": "雷赛智能",
      "orgId": "9900023947",
      "announcementId": "1224747280",
      "announcementTitle": "2025年三季度报告",
      "announcementTime": 1761580800000,
      "adjunctUrl": "finalpage/2025-10-28/1224747280.PDF",
      "adjunctSize": 207,
      "adjunctType": "PDF",
      "storageTime": null,
      "columnId": "09020202||250101||251302",
      "pageColumn": "SZZB",
      "announcementType": "01010503||010112||010307",
      "associateAnnouncement": null,
      "important": null,
      "batchNum": null,
      "announcementContent": "",
      "orgName": null,
      "tileSecName": "雷赛智能",
      "shortTitle": "2025年三季度报告",
      "announcementTypeName": null,
      "secNameList": null
    },
    {
      "id": null,
      "secCode": "002979",
      "secName": "雷赛智能",
      "orgId": "9900023947",
      "announcementId": "1223270439",
      "announcementTitle": "2024年年度报告",
      "announcementTime": 1745510400000,
      "adjunctUrl": "finalpage/2025-04-25/1223270439.PDF",
      "adjunctSize": 4511,
      "adjunctType": "PDF",
      "storageTime": null,
      "columnId": "09020202||250101||251302",
      "pageColumn": "SZZB",
      "announcementType": "01010503||010112||010301",
      "associateAnnouncement": null,
      "important": null,
      "batchNum": null,
      "announcementContent": "",
      "orgName": null,
      "tileSecName": "雷赛智能",
      "shortTitle": "2024年年度报告",
      "announcementTypeName": null,
      "secNameList": null
    },
    {
      "id": null,
      "secCode": "002979",
      "secName": "雷赛智能",
      "orgId": "9900023947",
      "announcementId": "1223270435",
      "announcementTitle": "2024年年度报告摘要",
      "announcementTime": 1745510400000,
      "adjunctUrl": "finalpage/2025-04-25/1223270435.PDF",
      "adjunctSize": 587,
      "adjunctType": "PDF",
      "storageTime": null,
      "columnId": "09020202||250101||251302",
      "pageColumn": "SZZB",
      "announcementType": "01010503||010112||010301",
      "associateAnnouncement": null,
      "important": null,
      "batchNum": null,
      "announcementContent": "",
      "orgName": null,
      "tileSecName": "雷赛智能",
      "shortTitle": "2024年年度报告摘要",
      "announcementTypeName": null,
      "secNameList": null
    },
    {
      "id": null,
      "secCode": "002979",
      "secName": "雷赛智能",
      "orgId": "9900023947",
      "announcementId": "1223270405",
      "announcementTitle": "2025年一季度报告",
      "announcementTime": 1745510400000,
      "adjunctUrl": "finalpage/2025-04-25/1223270405.PDF",
      "adjunctSize": 680,
      "adjunctType": "PDF",
      "storageTime": null,
      "columnId": "09020202||250101||251302",
      "pageColumn": "SZZB",
      "announcementType": "01010503||010112||010305",
      "associateAnnouncement": null,
      "important": null,
      "batchNum": null,
      "announcementContent": "",
      "orgName": null,
      "tileSecName": "雷赛智能",
      "shortTitle": "2025年一季度报告",
      "announcementTypeName": null,
      "secNameList": null
    }
  ],
  "categoryList": null,
  "hasMore": false,
  "totalpages": 0
}